Workbook

Sheet Summary
A1: LLM Catalogue - Non-Chinese vs Chinese
A2: Snapshot 31 July 2026. Primary source: live OpenRouter model API (365 entries, alias pointers, :batch and :free billing variants removed), plus manually added models that do not route through OpenRouter.
A3: Classification is by lab headquarters, not training data or hosting. Rows with 'UNVERIFIED' in the notes column are open/closed calls I could not confirm - check before relying on them.
A5: Counts
A6: Category | B6: Open weights | C6: Closed / API-only | D6: Total
A7: Non-Chinese | B7: =COUNTIF('Non-Chinese'!$D$5:$D$209,"Open") -> 73 | C7: =COUNTIF('Non-Chinese'!$D$5:$D$209,"Closed") -> 132 | D7: =B7+C7 -> 205
A8: Chinese | B8: =COUNTIF(Chinese!$D$5:$D$118,"Open") -> 90 | C8: =COUNTIF(Chinese!$D$5:$D$118,"Closed") -> 24 | D8: =B8+C8 -> 114
A9: Total | B9: =B7+B8 -> 163 | C9: =C7+C8 -> 156 | D9: =D7+D8 -> 319
A11: Models per lab
A12: Lab | B12: Category | C12: Open | D12: Closed | E12: Total
A13: Alibaba (Qwen) | B13: Chinese | C13: =COUNTIFS(Chinese!$B$5:$B$118,$A13,Chinese!$D$5:$D$118,"Open") -> 34 | D13: =COUNTIFS(Chinese!$B$5:$B$118,$A13,Chinese!$D$5:$D$118,"Closed") -> 14 | E13: =C13+D13 -> 48
A14: Ant Group (InclusionAI) | B14: Chinese | C14: =COUNTIFS(Chinese!$B$5:$B$118,$A14,Chinese!$D$5:$D$118,"Open") -> 3 | D14: =COUNTIFS(Chinese!$B$5:$B$118,$A14,Chinese!$D$5:$D$118,"Closed") -> 0 | E14: =C14+D14 -> 3
A15: Baidu | B15: Chinese | C15: =COUNTIFS(Chinese!$B$5:$B$118,$A15,Chinese!$D$5:$D$118,"Open") -> 1 | D15: =COUNTIFS(Chinese!$B$5:$B$118,$A15,Chinese!$D$5:$D$118,"Closed") -> 1 | E15: =C15+D15 -> 2
A16: ByteDance | B16: Chinese | C16: =COUNTIFS(Chinese!$B$5:$B$118,$A16,Chinese!$D$5:$D$118,"Open") -> 1 | D16: =COUNTIFS(Chinese!$B$5:$B$118,$A16,Chinese!$D$5:$D$118,"Closed") -> 1 | E16: =C16+D16 -> 2
A17: ByteDance Seed | B17: Chinese | C17: =COUNTIFS(Chinese!$B$5:$B$118,$A17,Chinese!$D$5:$D$118,"Open") -> 0 | D17: =COUNTIFS(Chinese!$B$5:$B$118,$A17,Chinese!$D$5:$D$118,"Closed") -> 4 | E17: =C17+D17 -> 4
A18: DeepSeek | B18: Chinese | C18: =COUNTIFS(Chinese!$B$5:$B$118,$A18,Chinese!$D$5:$D$118,"Open") -> 12 | D18: =COUNTIFS(Chinese!$B$5:$B$118,$A18,Chinese!$D$5:$D$118,"Closed") -> 0 | E18: =C18+D18 -> 12
A19: iFlytek | B19: Chinese | C19: =COUNTIFS(Chinese!$B$5:$B$118,$A19,Chinese!$D$5:$D$118,"Open") -> 0 | D19: =COUNTIFS(Chinese!$B$5:$B$118,$A19,Chinese!$D$5:$D$118,"Closed") -> 1 | E19: =C19+D19 -> 1
A20: Kuaishou (Kwaipilot) | B20: Chinese | C20: =COUNTIFS(Chinese!$B$5:$B$118,$A20,Chinese!$D$5:$D$118,"Open") -> 3 | D20: =COUNTIFS(Chinese!$B$5:$B$118,$A20,Chinese!$D$5:$D$118,"Closed") -> 0 | E20: =C20+D20 -> 3
A21: Meituan | B21: Chinese | C21: =COUNTIFS(Chinese!$B$5:$B$118,$A21,Chinese!$D$5:$D$118,"Open") -> 1 | D21: =COUNTIFS(Chinese!$B$5:$B$118,$A21,Chinese!$D$5:$D$118,"Closed") -> 0 | E21: =C21+D21 -> 1
A22: MiniMax | B22: Chinese | C22: =COUNTIFS(Chinese!$B$5:$B$118,$A22,Chinese!$D$5:$D$118,"Open") -> 8 | D22: =COUNTIFS(Chinese!$B$5:$B$118,$A22,Chinese!$D$5:$D$118,"Closed") -> 0 | E22: =C22+D22 -> 8
A23: Moonshot AI | B23: Chinese | C23: =COUNTIFS(Chinese!$B$5:$B$118,$A23,Chinese!$D$5:$D$118,"Open") -> 7 | D23: =COUNTIFS(Chinese!$B$5:$B$118,$A23,Chinese!$D$5:$D$118,"Closed") -> 0 | E23: =C23+D23 -> 7
A24: Nex AGI | B24: Chinese | C24: =COUNTIFS(Chinese!$B$5:$B$118,$A24,Chinese!$D$5:$D$118,"Open") -> 2 | D24: =COUNTIFS(Chinese!$B$5:$B$118,$A24,Chinese!$D$5:$D$118,"Closed") -> 0 | E24: =C24+D24 -> 2
... A30: Zhipu AI / Z.ai | B30: Chinese | C30: =COUNTIFS(Chinese!$B$5:$B$118,$A30,Chinese!$D$5:$D$118,"Open") -> 12 | D30: =COUNTIFS(Chinese!$B$5:$B$118,$A30,Chinese!$D$5:$D$118,"Closed") -> 0 | E30: =C30+D30 -> 12
A31: AI Singapore | B31: Non-Chinese | C31: =COUNTIFS('Non-Chinese'!$B$5:$B$209,$A31,'Non-Chinese'!$D$5:$D$209,"Open") -> 1 | D31: =COUNTIFS('Non-Chinese'!$B$5:$B$209,$A31,'Non-Chinese'!$D$5:$D$209,"Closed") -> 0 | E31: =C31+D31 -> 1
A32: AI21 Labs | B32: Non-Chinese | C32: =COUNTIFS('Non-Chinese'!$B$5:$B$209,$A32,'Non-Chinese'!$D$5:$D$209,"Open") -> 1 | D32: =COUNTIFS('Non-Chinese'!$B$5:$B$209,$A32,'Non-Chinese'!$D$5:$D$209,"Closed") -> 0 | E32: =C32+D32 -> 1
A33: Aion Labs | B33: Non-Chinese | C33: =COUNTIFS('Non-Chinese'!$B$5:$B$209,$A33,'Non-Chinese'!$D$5:$D$209,"Open") -> 1 | D33: =COUNTIFS('Non-Chinese'!$B$5:$B$209,$A33,'Non-Chinese'!$D$5:$D$209,"Closed") -> 3 | E33: =C33+D33 -> 4
A34: Allen Institute for AI | B34: Non-Chinese | C34: =COUNTIFS('Non-Chinese'!$B$5:$B$209,$A34,'Non-Chinese'!$D$5:$D$209,"Open") -> 2 | D34: =COUNTIFS('Non-Chinese'!$B$5:$B$209,$A34,'Non-Chinese'!$D$5:$D$209,"Closed") -> 0 | E34: =C34+D34 -> 2
A35: Amazon | B35: Non-Chinese | C35: =COUNTIFS('Non-Chinese'!$B$5:$B$209,$A35,'Non-Chinese'!$D$5:$D$209,"Open") -> 0 | D35: =COUNTIFS('Non-Chinese'!$B$5:$B$209,$A35,'Non-Chinese'!$D$5:$D$209,"Closed") -> 5 | E35: =C35+D35 -> 5
A36: Anthracite (community) | B36: Non-Chinese | C36: =COUNTIFS('Non-Chinese'!$B$5:$B$209,$A36,'Non-Chinese'!$D$5:$D$209,"Open") -> 1 | D36: =COUNTIFS('Non-Chinese'!$B$5:$B$209,$A36,'Non-Chinese'!$D$5:$D$209,"Closed") -> 0 | E36: =C36+D36 -> 1
A37: Anthropic | B37: Non-Chinese | C37: =COUNTIFS('Non-Chinese'!$B$5:$B$209,$A37,'Non-Chinese'!$D$5:$D$209,"Open") -> 0 | D37: =COUNTIFS('Non-Chinese'!$B$5:$B$209,$A37,'Non-Chinese'!$D$5:$D$209,"Closed") -> 18 | E37: =C37+D37 -> 18
A38: Arcee AI | B38: Non-Chinese | C38: =COUNTIFS('Non-Chinese'!$B$5:$B$209,$A38,'Non-Chinese'!$D$5:$D$209,"Open") -> 2 | D38: =COUNTIFS('Non-Chinese'!$B$5:$B$209,$A38,'Non-Chinese'!$D$5:$D$209,"Closed") -> 0 | E38: =C38+D38 -> 2
A39: Cognitive Computations | B39: Non-Chinese | C39: =COUNTIFS('Non-Chinese'!$B$5:$B$209,$A39,'Non-Chinese'!$D$5:$D$209,"Open") -> 1 | D39: =COUNTIFS('Non-Chinese'!$B$5:$B$209,$A39,'Non-Chinese'!$D$5:$D$209,"Closed") -> 0 | E39: =C39+D39 -> 1
A40: Cohere | B40: Non-Chinese | C40: =COUNTIFS('Non-Chinese'!$B$5:$B$209,$A40,'Non-Chinese'!$D$5:$D$209,"Open") -> 5 | D40: =COUNTIFS('Non-Chinese'!$B$5:$B$209,$A40,'Non-Chinese'!$D$5:$D$209,"Closed") -> 0 | E40: =C40+D40 -> 5
A41: Deep Cogito | B41: Non-Chinese | C41: =COUNTIFS('Non-Chinese'!$B$5:$B$209,$A41,'Non-Chinese'!$D$5:$D$209,"Open") -> 1 | D41: =COUNTIFS('Non-Chinese'!$B$5:$B$209,$A41,'Non-Chinese'!$D$5:$D$209,"Closed") -> 0 | E41: =C41+D41 -> 1
A42: Google DeepMind | B42: Non-Chinese | C42: =COUNTIFS('Non-Chinese'!$B$5:$B$209,$A42,'Non-Chinese'!$D$5:$D$209,"Open") -> 7 | D42: =COUNTIFS('Non-Chinese'!$B$5:$B$209,$A42,'Non-Chinese'!$D$5:$D$209,"Closed") -> 21 | E42: =C42+D42 -> 28
... A69: xAI | B69: Non-Chinese | C69: =COUNTIFS('Non-Chinese'!$B$5:$B$209,$A69,'Non-Chinese'!$D$5:$D$209,"Open") -> 0 | D69: =COUNTIFS('Non-Chinese'!$B$5:$B$209,$A69,'Non-Chinese'!$D$5:$D$209,"Closed") -> 5 | E69: =C69+D69 -> 5
A70: Total | C70: =SUM(C13:C69) -> 163 | D70: =SUM(D13:D69) -> 156 | E70: =SUM(E13:E69) -> 319
A72: Legend
A73: - Open = weights downloadable. Licence still varies widely: MIT/Apache (DeepSeek, GLM, Qwen, gpt-oss) vs restrictive (Llama Community, Gemma Terms, Cohere CC-BY-NC).
A74: - Closed = hosted API only, no weights published.
A75: - Pricing is OpenRouter's cheapest listed rate per million tokens at fetch time; blank where not published.
A76: - Labs shipping both open and closed lines (Alibaba, Mistral, ByteDance, Tencent, Baidu) appear in both counts.
A77: - Community fine-tunes (TheDrummer, Sao10K, Gryphe, Undi95, Anthracite) are derivatives, not base models.
A79: Added 31 Jul 2026
A80: Parameters | B80: 163 benchmark parameters grouped by evaluation axis. 78 are new gaps not yet in build_workbook.py; 85 already exist in the harness.
A81: How to Test | B81: Step-by-step procedure for all four testing paths: platform login, hosted API (open-weight), hosted API (closed), and local DGX - plus where latency is valid.
A82: Prompts | B82: 174 test prompts across 8 suites - 68 new, 106 already in prompts/. Every new expected value verified against graders.py before writing.

Sheet Parameters
A1: Benchmark parameter dictionary
A2: Every parameter worth measuring, grouped by evaluation axis. 'In workbook' = already defined in build_workbook.py's Parameters sheet. 'NEW - add' = gap identified 31 Jul 2026, not yet in the harness.
A3: Core = collect for every run. Optional = collect where relevant. Read the 'How to Test' sheet for the procedure that produces these numbers.
A5: Axis | B5: Parameter | C5: Field name | D5: Unit | E5: Definition / why it matters | F5: How to measure | G5: Sheet | H5: Priority | I5: Status
A6: ACCURACY
A7: Accuracy | B7: Task accuracy | C7: score_mean | D7: 0-1 | E7: Primary metric for the task suite (accuracy, pass@1, F1). | F7: Deterministic graders in graders.py. | G7: Quality_Results | H7: Core | I7: In workbook
A8: Accuracy | B8: Score dispersion | C8: score_stdev | D8: 0-1 | E8: Stdev over every graded item, not over repeats. | F8: Runner computes it. | G8: Quality_Results | H8: Core | I8: In workbook
A9: Accuracy | B9: 95% confidence interval | C9: score_ci95_halfwidth | D9: pts | E9: 1.96*stdev/sqrt(n*repeats). If two models' intervals overlap they are tied. | F9: Formula. Grow n_samples to narrow it. | G9: Quality_Results | H9: Core | I9: In workbook
A10: Accuracy | B10: Sample size | C10: n_samples | D10: count | E10: Graded items behind the score. 15 gives about +/-22 pts; 100 gives +/-9; 600 gives +/-4. | F10: Suite size. | G10: Quality_Results | H10: Core | I10: In workbook
A11: Accuracy | B11: Repeats | C11: repeats | D11: count | E11: Runs per configuration. | F11: Run_Config. | G11: Quality_Results | H11: Core | I11: In workbook
A12: Accuracy | B12: Metric name | C12: metric_name | D12: text | E12: Which metric score_mean holds - accuracy, pass@1, F1, exec-match. | F12: Runner records it. | G12: Quality_Results | H12: Core | I12: In workbook
A13: Accuracy | B13: Hallucination rate | C13: hallucination_rate_pct | D13: % | E13: Unsupported claims or answers to unanswerable questions. | F13: Grounded QA set (extraction suite). | G13: Quality_Results | H13: Core | I13: In workbook
A14: Accuracy | B14: Quantization delta | C14: delta_vs_fp16_pct | D14: % | E14: Quality lost against the BF16 baseline of the same model. | F14: Formula vs fp16_baseline_score. | G14: Quality_Results | H14: Core | I14: In workbook
A15: Accuracy | B15: Verbosity | C15: avg_output_tokens | D15: tokens | E15: A model answering in 3x the tokens costs 3x to serve. | F15: Harness. | G15: Quality_Results | H15: Core | I15: In workbook
A16: Accuracy | B16: Judge model | C16: judge_model | D16: text | E16: Model used for any LLM-as-judge scoring. Must not be a contestant. | F16: Record it; 'none' for deterministic graders. | G16: Quality_Results | H16: Core | I16: In workbook
A17: Accuracy | B17: Calibration error | C17: ece | D17: 0-1 | E17: Expected calibration error - gap between stated confidence and actual correctness. | F17: Bin predictions by confidence, compare to accuracy. | G17: Quality_Results | H17: Optional | I17: NEW - add
A18: Accuracy | B18: Abstention rate | C18: abstention_rate_pct | D18: % | E18: Says 'I don't know' when it should. High accuracy with zero abstention on unanswerable items is a red flag. | F18: Unanswerable subset of the extraction suite. | G18: Quality_Results | H18: Core | I18: NEW - add
... A24: Accuracy | B24: Prompt-sensitivity | C24: prompt_variant_delta_pct | D24: pts | E24: Score change from a reworded but semantically identical prompt. | F24: Two phrasings of the same suite. | G24: Quality_Results | H24: Optional | I24: NEW - add
A25: LATENCY
A26: Latency | B26: Time to first token | C26: ttft_p50_ms / p95 / p99 | D26: ms | E26: The number a user feels first. | F26: Client, streaming mode only. | G26: Perf_Results | H26: Core | I26: In workbook
A27: Latency | B27: Time per output token | C27: tpot_p50_ms / p99 | D27: ms | E27: Perceived typing speed after the first token. | F27: (e2e - ttft) / (out_tokens - 1). | G27: Perf_Results | H27: Core | I27: In workbook
A28: Latency | B28: Inter-token latency | C28: itl_p50_ms | D28: ms | E28: Gap between consecutive tokens; exposes scheduler stalls. | F28: Timestamp every stream chunk. | G28: Perf_Results | H28: Optional | I28: In workbook
A29: Latency | B29: End to end | C29: e2e_p50_ms / p95 / p99 | D29: ms | E29: Request submit to last token. | F29: Client. | G29: Perf_Results | H29: Core | I29: In workbook
A30: Latency | B30: Per-request output rate | C30: output_tps_per_request | D30: tok/s | E30: Decode speed a single user sees. | F30: Client. | G30: Perf_Results | H30: Core | I30: In workbook
A31: Latency | B31: Total output throughput | C31: total_output_tps | D31: tok/s | E31: System-wide capacity number. | F31: Client. | G31: Perf_Results | H31: Core | I31: In workbook
A32: Latency | B32: Total throughput | C32: total_throughput_tps | D32: tok/s | E32: Input + output tokens/s, comparable across shapes. | F32: Client. | G32: Perf_Results | H32: Core | I32: In workbook
A33: Latency | B33: Requests per second | C33: requests_per_s | D33: req/s | E33: Completed requests/s at this load point. | F33: Client. | G33: Perf_Results | H33: Core | I33: In workbook
A34: Latency | B34: Output tok/s per GPU | C34: output_tps_per_gpu | D34: tok/s | E34: Throughput normalised by GPUs actually used. | F34: Formula. | G34: Perf_Results | H34: Core | I34: In workbook
A35: Latency | B35: Cold start | C35: model_load_time_s | D35: s | E35: Process start to ready-to-serve. | F35: Engine log / Ollama load_duration. | G35: Perf_Results | H35: Optional | I35: In workbook
A36: Latency | B36: Time to first ANSWER token | C36: ttfat_ms | D36: ms | E36: On reasoning models TTFT is meaningless - the user waits through the whole thinking block. This is the real perceived latency. | F36: First token after the </think> boundary. | G36: Perf_Results | H36: Core | I36: NEW - add
A37: Latency | B37: Queue wait vs compute | C37: queue_time_ms | D37: ms | E37: Separates scheduler backlog from model speed. High queue time means you are measuring the server, not the model. | F37: Engine metrics endpoint (vLLM exposes it). | G37: Perf_Results | H37: Optional | I37: NEW - add
... A40: Latency | B40: Streaming vs non-streaming | C40: stream_enabled | D40: Y/N | E40: Non-streaming hides TTFT entirely. Record which mode produced the row. | F40: Client flag. | G40: Perf_Results | H40: Core | I40: NEW - add
A41: REASONING
A42: Reasoning | B42: Reasoning suite accuracy | C42: score_mean where capability='reasoning' | D42: 0-1 | E42: Multi-step word problems, algebra, logic. | F42: prompts/reasoning.jsonl. | G42: Quality_Results | H42: Core | I42: In workbook
A43: Reasoning | B43: Reasoning tokens emitted | C43: reasoning_tokens_mean | D43: tokens | E43: Thinking tokens, counted separately from answer tokens. Drives cost more than anything else on R1/Qwen3/GLM-class models. | F43: usage.reasoning_tokens, or count inside <think> tags. | G43: Quality_Results | H43: Core | I43: NEW - add
A44: Reasoning | B44: Accuracy vs thinking budget | C44: score_at_budget_1k / 4k / 16k | D44: 0-1 | E44: The curve, not one point. Where it flattens is your production max_tokens. | F44: Re-run the suite at three max_tokens caps. | G44: Quality_Results | H44: Core | I44: NEW - add
A45: Reasoning | B45: Overthinking rate | C45: reasoning_tokens_on_trivial | D45: tokens | E45: Thinking tokens spent on questions a 7B answers instantly. Pure waste. | F45: Reasoning tokens on the easiest suite decile. | G45: Quality_Results | H45: Optional | I45: NEW - add
A46: Reasoning | B46: Thinking mode | C46: thinking_mode | D46: on/off/auto | E46: Qwen3 /think, DeepSeek DeepThink, GLM toggle. Score both modes; never compare across them. | F46: Request parameter or prompt prefix. | G46: Quality_Results | H46: Core | I46: NEW - add
A47: Reasoning | B47: Truncation at limit | C47: hit_max_tokens_pct | D47: % | E47: Ran out of budget mid-thought. Produces a confident wrong answer with no error. | F47: finish_reason == 'length'. | G47: Quality_Results | H47: Core | I47: NEW - add
A48: Reasoning | B48: Multi-step task completion | C48: task_completion_pct | D48: % | E48: Full trajectory succeeded, not just the final answer. | F48: Agentic harness with step checks. | G48: Quality_Results | H48: Optional | I48: NEW - add
A49: Reasoning | B49: Step-level correctness | C49: process_score | D49: 0-1 | E49: Fraction of intermediate steps correct. Catches right-answer-wrong-method. | F49: Process reward model or manual audit. | G49: Quality_Results | H49: Optional | I49: NEW - add
A50: Reasoning | B50: Public reasoning suites | C50: task_suite | D50: text | E50: GPQA-Diamond, AIME, MATH-500, BBH, MuSR, ZebraLogic, LiveBench. | F50: Record which suite produced the row. | G50: Quality_Results | H50: Optional | I50: NEW - add
A51: LANGUAGE (ENGLISH)
A52: Language (English) | B52: Per-language score | C52: language | D52: text | E52: Score split by language. Every current prompt is en. | F52: Split the suite by the language field. | G52: Quality_Results | H52: Core | I52: In workbook
A53: Language (English) | B53: Instruction compliance | C53: instruction_compliance_pct | D53: % | E53: Verifiable-constraint adherence: word counts, bullet counts, forbidden words, casing. | F53: constraint_check grader. | G53: Quality_Results | H53: Core | I53: In workbook
A54: Language (English) | B54: Grammar error rate | C54: grammar_errors_per_1k_words | D54: count | E54: Fluency floor for customer-facing output. | F54: LanguageTool or similar, on generated text. | G54: Quality_Results | H54: Optional | I54: NEW - add
A55: Language (English) | B55: Readability | C55: flesch_kincaid_grade | D55: grade | E55: Reading level of the output. Matters when a human is the consumer. | F55: textstat on the response corpus. | G55: Quality_Results | H55: Optional | I55: NEW - add
A56: Language (English) | B56: Spelling-variant consistency | C56: en_variant_drift_pct | D56: % | E56: US and UK spellings mixed inside one response. | F56: Word-list diff over the output. | G56: Quality_Results | H56: Optional | I56: NEW - add
A57: Language (English) | B57: Long-form coherence | C57: coherence_score | D57: 0-1 | E57: Holds a thread over 2k+ token outputs. Needs a judge or a human. | F57: Rubric scoring on long-form prompts. | G57: Quality_Results | H57: Optional | I57: NEW - add
A58: Language (English) | B58: Tone / register adherence | C58: style_compliance_pct | D58: % | E58: Follows 'formal', 'concise', or a brand voice instruction. | F58: Rubric or constraint checks. | G58: Quality_Results | H58: Optional | I58: NEW - add
A59: Language (English) | B59: Non-English token leakage | C59: stray_token_pct | D59: % | E59: CJK characters or stray markdown appearing in English output. Worth a rate given how many candidates are Chinese-lab models. | F59: Unicode range scan over responses. | G59: Quality_Results | H59: Core | I59: NEW - add
A60: Language (English) | B60: Code-switch robustness | C60: codeswitch_score | D60: 0-1 | E60: Handles non-English fragments embedded in an English prompt. | F60: Mixed-script prompt subset. | G60: Quality_Results | H60: Optional | I60: NEW - add
A61: TECHNICAL
A62: Technical | B62: Coding pass@1 | C62: pass_at_1 | D62: % | E62: Fraction solved first attempt, verified by real unit tests. | F62: code_exec grader, --allow-code-exec. | G62: Quality_Results | H62: Core | I62: In workbook
A63: Technical | B63: Valid JSON rate | C63: valid_json_rate_pct | D63: % | E63: Parses and validates against the schema, even when wrapped in prose. | F63: json_schema grader. | G63: Quality_Results | H63: Core | I63: In workbook
A64: Technical | B64: Tool-calling accuracy | C64: task_name = tool_* | D64: % | E64: Right tool chosen, arguments well-formed. | F64: tool_call grader. | G64: Quality_Results | H64: Core | I64: In workbook
A65: Technical | B65: Long-context retrieval | C65: task_name = needle_* | D65: % | E65: Retrieval accuracy by length and depth. Report the whole curve. | F65: Generated needle suite, --needle. | G65: Quality_Results | H65: Core | I65: In workbook
A66: Technical | B66: Extraction accuracy | C66: score_mean where suite='extraction' | D66: 0-1 | E66: Grounded QA over supplied documents. | F66: prompts/extraction.jsonl. | G66: Quality_Results | H66: Core | I66: In workbook
A67: Technical | B67: Effective context length | C67: effective_context_tokens | D67: tokens | E67: Where retrieval accuracy falls below 85%. Almost never equals the advertised window - Llama 4's 10M claim needs this. | F67: Needle sweep, find the knee. | G67: Quality_Results | H67: Core | I67: NEW - add
A68: Technical | B68: Build / compile success | C68: build_success_pct | D68: % | E68: Generated code compiles or runs at all. Separates 'looks right' from 'works'. | F68: Subprocess compile step. | G68: Quality_Results | H68: Core | I68: NEW - add
A69: Technical | B69: Patch applies cleanly | C69: patch_apply_pct | D69: % | E69: Generated diffs apply without conflict. The real failure mode in agentic coding. | F69: git apply --check. | G69: Quality_Results | H69: Optional | I69: NEW - add
A70: Technical | B70: Repo-level task completion | C70: swebench_verified_pct | D70: % | E70: Multi-file changes that make the tests pass. | F70: SWE-bench Verified harness. | G70: Quality_Results | H70: Optional | I70: NEW - add
A71: Technical | B71: SQL execution accuracy | C71: exec_match_pct | D71: % | E71: Query returns the right rows, not the right-looking string. | F71: Execute against a fixture DB. | G71: Quality_Results | H71: Optional | I71: NEW - add
A72: Technical | B72: Grounding / citation faithfulness | C72: attribution_precision_pct | D72: % | E72: Every claim traceable to the supplied context. The RAG metric that matters. | F72: Claim-to-source matching. | G72: Quality_Results | H72: Core | I72: NEW - add
A73: Technical | B73: Numeric and unit correctness | C73: unit_error_pct | D73: % | E73: Wrong units pass most string graders silently. | F73: Unit-aware comparison on numeric answers. | G73: Quality_Results | H73: Optional | I73: NEW - add
... A75: Technical | B75: Regression vs previous model | C75: delta_vs_incumbent_pct | D75: pts | E75: Change against whatever you run today. A model that wins on average can still regress your top workflow. | F75: Same golden set, both models. | G75: Quality_Results | H75: Core | I75: NEW - add
A76: FINE-TUNING
A77: Fine-tuning | B77: License permits FT + redistribution | C77: ft_license_ok | D77: Y/N/cond | E77: Gemma Terms and Cohere CC-BY-NC restrict it; MIT/Apache do not. CHECK THIS FIRST - it eliminates candidates before any benchmark runs. | F77: Read the LICENSE and the acceptable-use policy. | G77: Models | H77: Core | I77: NEW - add
A78: Fine-tuning | B78: Base checkpoint available | C78: base_checkpoint_available | D78: Y/N | E78: Instruct-only releases are materially harder to tune. | F78: Hugging Face repo listing. | G78: Models | H78: Core | I78: NEW - add
A79: Fine-tuning | B79: Trainable parameters | C79: trainable_params_b | D79: billions | E79: Full fine-tune vs adapter. | F79: Model config. | G79: Models | H79: Core | I79: NEW - add
A80: Fine-tuning | B80: LoRA rank / alpha | C80: lora_rank / lora_alpha | D80: int | E80: Adapter capacity. | F80: Training config. | G80: Models | H80: Core | I80: NEW - add
A81: Fine-tuning | B81: VRAM: full fine-tune | C81: vram_full_ft_gb | D81: GB | E81: Roughly 16-20 bytes per parameter with Adam. Decides whether it fits the DGX at all. | F81: Measure, or estimate from params. | G81: Models | H81: Core | I81: NEW - add
A82: Fine-tuning | B82: VRAM: LoRA / QLoRA | C82: vram_lora_gb / vram_qlora_gb | D82: GB | E82: The practical path for anything over 30B. | F82: Measure during a short run. | G82: Models | H82: Core | I82: NEW - add
A83: Fine-tuning | B83: Training throughput | C83: train_tokens_per_s | D83: tok/s | E83: Sequence-packed tokens per second. | F83: Trainer logs. | G83: Models | H83: Core | I83: NEW - add
A84: Fine-tuning | B84: Model FLOPs utilisation | C84: mfu_pct | D84: % | E84: How much of the GPU you are actually using. Below 30% means the recipe, not the hardware, is the limit. | F84: Achieved FLOPs / peak FLOPs. | G84: Models | H84: Optional | I84: NEW - add
A85: Fine-tuning | B85: Epochs to converge | C85: epochs_to_converge | D85: count | E85: Where held-out loss stops improving. | F85: Eval loss curve. | G85: Models | H85: Core | I85: NEW - add
A86: Fine-tuning | B86: Training GPU-hours and cost | C86: train_gpu_hours / train_cost_usd | D86: h / USD | E86: Priced through Cost_Model at $/GPU-hour. | F86: Wall clock x GPUs. | G86: Models | H86: Core | I86: NEW - add
A87: Fine-tuning | B87: Data volume needed | C87: n_train_examples | D87: count | E87: Measure at 500 / 2k / 10k. The curve tells you whether more data helps or you have hit the ceiling. | F87: Train three adapters, compare. | G87: Models | H87: Core | I87: NEW - add
A88: Fine-tuning | B88: Held-out gain | C88: delta_vs_base_pct | D88: pts | E88: Improvement on YOUR task after tuning. The whole point. | F88: Golden set, base vs tuned. | G88: Models | H88: Core | I88: NEW - add
... A98: Fine-tuning | B98: Training seed / reproducibility | C98: train_seed | D98: int | E98: Two runs at the same seed should land within noise. | F98: Trainer config. | G98: Models | H98: Core | I98: NEW - add
A99: SAFETY
A100: Safety | B100: Refusal rate on benign prompts | C100: refusal_rate_pct | D100: % | E100: The over-refusal tax. Every prompt in the refusal suite is benign, so a refusal is a false positive. | F100: refusal_check grader. | G100: Quality_Results | H100: Core | I100: In workbook
A101: Safety | B101: Jailbreak resistance | C101: jailbreak_success_pct | D101: % | E101: Fraction of adversarial prompts that succeed. Lower is better. | F101: Public red-team set, held privately. | G101: Quality_Results | H101: Core | I101: NEW - add
A102: Safety | B102: Prompt-injection resistance | C102: injection_success_pct | D102: % | E102: Instructions embedded in retrieved documents that the model obeys. Critical for any RAG or agent deployment. | F102: Injected-document test set. | G102: Quality_Results | H102: Core | I102: NEW - add
A103: Safety | B103: PII leakage rate | C103: pii_leak_pct | D103: % | E103: Emits personal data from context when asked not to, or memorised from training. | F103: Canary PII in context + extraction attempts. | G103: Quality_Results | H103: Optional | I103: NEW - add
A104: Safety | B104: Toxicity rate | C104: toxicity_pct | D104: % | E104: Unsafe output on neutral prompts. | F104: Classifier over responses. | G104: Quality_Results | H104: Optional | I104: NEW - add
A105: COST
A106: Cost | B106: Cost per 1M output tokens | C106: cost_per_1m_out_usd | D106: USD | E106: GPU-hours consumed priced through Cost_Model. | F106: Formula. | G106: Perf_Results | H106: Core | I106: In workbook
A107: Cost | B107: Derived $/GPU-hour | C107: cost_per_gpu_hour_usd | D107: USD | E107: All-in amortised cost of one GPU for one hour. | F107: Formula from capex + power. | G107: Cost_Model | H107: Core | I107: In workbook
A108: Cost | B108: System capex | C108: system_capex_usd | D108: USD | E108: Purchase price of the DGX system. | F108: Invoice. | G108: Cost_Model | H108: Core | I108: In workbook
A109: Cost | B109: Amortisation period | C109: amortisation_years | D109: years | E109: Depreciation window. | F109: Finance policy. | G109: Cost_Model | H109: Core | I109: In workbook
A110: Cost | B110: Annual utilisation | C110: annual_utilisation | D110: % | E110: Fraction of the year the GPUs actually serve. | F110: Estimate or measure. | G110: Cost_Model | H110: Core | I110: In workbook
A111: Cost | B111: System power draw | C111: system_power_kw | D111: kW | E111: Sustained wall power under load. | F111: PDU reading. | G111: Cost_Model | H111: Core | I111: In workbook
A112: Cost | B112: PUE | C112: pue | D112: ratio | E112: Datacentre power usage effectiveness. | F112: Facilities. | G112: Cost_Model | H112: Core | I112: In workbook
A113: Cost | B113: Electricity price | C113: electricity_usd_per_kwh | D113: USD/kWh | E113: Blended tariff. | F113: Utility bill. | G113: Cost_Model | H113: Core | I113: In workbook
A114: Cost | B114: Break-even vs API | C114: - | D114: - | E114: Self-hosted $/1M against the API price of the closest model. | F114: Manual comparison. | G114: Summary | H114: Optional | I114: In workbook
A115: Cost | B115: API list price | C115: api_price_in_usd_per_m / api_price_out_usd_per_m | D115: USD/M | E115: Published per-million rates. Already populated for every model in the Non-Chinese and Chinese sheets of this workbook. | F115: Provider pricing page. | G115: Models | H115: Core | I115: NEW - add
A116: Cost | B116: Cost per completed task | C116: cost_per_task_usd | D116: USD | E116: Price x tokens actually consumed on YOUR workload. A cheap model that needs 3x the tokens is not cheap. | F116: avg tokens x price, per suite. | G116: Quality_Results | H116: Core | I116: NEW - add
A117: Cost | B117: Reasoning-token cost share | C117: reasoning_cost_pct | D117: % | E117: Share of the bill spent on thinking tokens the user never sees. | F117: reasoning_tokens x output price. | G117: Quality_Results | H117: Optional | I117: NEW - add
A118: RESOURCE
...

Sheet How to Test
A1: How to test these models
A2: Two paths. A platform login screens candidates cheaply; the API produces numbers you can defend. They answer different questions - do not mix their rows.
A4: Section | B4: Step | C4: What to do | D4: Command / detail
A5: WHICH PATH ANSWERS WHICH QUESTION
A6: Choosing a path | C6: Is this model good enough for my task? | D6: Web UI or API - both valid
A7: Choosing a path | C7: Which of these 5 models is best? | D7: API, scripted. A UI cannot reach n=100
A8: Choosing a path | C8: How fast is it for my users? | D8: API if you will deploy on API; DGX if self-hosting. NEVER from a web UI
A9: Choosing a path | C9: What will it cost? | D9: API list price, or DGX cost_per_1m_out_usd
A10: Choosing a path | C10: Can I fine-tune it? | D10: Neither - it is a license check plus a VRAM calculation
A11: STEP 0 - PREREQUISITES
A12: Prerequisites | B12: 0.1 | C12: Restore the repo. All 21 tracked files are currently deleted in the working tree. | D12: git restore .
A13: Prerequisites | B13: 0.2 | C13: Install dependencies. | D13: pip install openpyxl httpx jsonschema
A14: Prerequisites | B14: 0.3 | C14: Confirm the workbook exists and rebuild only if you have no collected data - rebuilding wipes it. | D14: python build_workbook.py
A15: PATH A - PLATFORM LOGIN (WEB UI)
A16: Path A - purpose | C16: Screening only. Use it to cut 20 candidates to 5. It is not a measurement tool. | D16: Expect +/-22 pts of noise at 15 hand-graded prompts
A17: Path A - where | B17: A.1 | C17: OpenRouter chat - one login, ~300 models, side-by-side comparison. Best single account. | D17: https://openrouter.ai/chat
A18: Path A - where | B18: A.2 | C18: NVIDIA build - open-weight models, and it shows the equivalent API snippet. | D18: https://build.nvidia.com
A19: Path A - where | B19: A.3 | C19: Hugging Face playground - the only route for OLMo, Falcon, EXAONE, Sarvam, SEA-LION. | D19: https://huggingface.co/playground
A20: Path A - where | B20: A.4 | C20: LM Arena - blind side-by-side. Use for calibration, never for scoring. | D20: https://lmarena.ai
A21: Path A - where | B21: A.5 | C21: First-party chat UIs for Chinese labs. | D21: chat.qwen.ai / chat.deepseek.com / chat.z.ai / kimi.com
A22: Path A - protocol | B22: A.6 | C22: RULE 1: new chat per prompt. Prior turns change the answer. | D22: Never run a whole suite in one thread
A23: Path A - protocol | B23: A.7 | C23: RULE 2: turn OFF web search, code interpreter and memory. A UI that silently searches is a RAG system, not the model. Biggest source of false results. | D23: Check the toggles before every session
A24: Path A - protocol | B24: A.8 | C24: RULE 3: record the reasoning toggle. Thinking-on vs thinking-off is not a comparison. | D24: Qwen /think, DeepSeek DeepThink, GLM toggle
A25: Path A - protocol | B25: A.9 | C25: RULE 4: paste prompts verbatim from your own suites - they avoid the public-benchmark contamination problem. | D25: prompts/*.jsonl
A26: Path A - protocol | B26: A.10 | C26: RULE 5: fix the scoring rule before you start. 1 = correct, 0 = not. Grade the answer, not the confidence. | D26: Write it down first
A27: Path A - limits | B27: A.11 | C27: Latency from a UI is your ISP plus their queue plus their frontend. Ignore the stopwatch entirely. | D27: Use Path B or the DGX for any timing
A28: Path A - limits | B28: A.12 | C28: Every consumer UI injects a system prompt that changes refusals, formatting and verbosity. UI refusals are not API refusals. | D28: Record system_prompt_id = 'platform default'
A29: Path A - recording | B29: A.13 | C29: Append hand-graded rows to Quality_Results, stamped so they can never be averaged into scripted runs. | D29: serving_stack=WEB:<platform>, judge_model=human
A30: PATH B - API, OPEN-WEIGHT MODELS
A31: Path B - purpose | C31: The path that produces defensible numbers. Same weights as local, so scores transfer. | D31: run_api_quality.py
A32: Path B - keys | B32: B.1 | C32: Copy the template. .env is gitignored. Never commit a key, never paste one into a chat window. | D32: cp .env.example .env
A33: Path B - keys | B33: B.2 | C33: Three keys cover all 25 registry models: OpenRouter (17), Hugging Face (9), NVIDIA (12). | D33: OPENROUTER_API_KEY / HF_TOKEN / NVIDIA_API_KEY
A34: Path B - keys | B34: B.3 | C34: Add Groq too. No extra coverage, but generous free limits cut wall-clock on a full sweep. | D34: GROQ_API_KEY
A35: Path B - verify | B35: B.4 | C35: Confirm which keys loaded. | D35: python run_api_quality.py --list-providers
A36: Path B - verify | B36: B.5 | C36: Resolve every model id against each provider's /models endpoint. Run before EVERY campaign - ids drift, and a stale id 404s exactly like a model scoring zero. | D36: python run_api_quality.py --check
A37: Path B - verify | B37: B.6 | C37: Expect misses today: mistral-small-24b-instruct-2501 and the Nemotron v1 entries are superseded. --check suggests near matches. | D37: Fix providers.json, re-run --check
A38: Path B - size | B38: B.7 | C38: Print the request count and wall-clock estimate before spending anything. | D38: python run_api_quality.py --dry-run --suites reasoning,knowledge
A39: Path B - run | B39: B.8 | C39: Smoke-test one model on one suite end to end. | D39: python run_api_quality.py --models qwen3-32b --suites reasoning --repeats 1
A40: Path B - run | B40: B.9 | C40: Main sweep across the deterministic suites. | D40: python run_api_quality.py --priority P0 --suites reasoning,knowledge,extraction,instruction_following,structured_output
A41: Path B - run | B41: B.10 | C41: Coding is a separate run - it executes model-written Python. Do it in a container. | D41: python run_api_quality.py --priority P0 --suites coding --allow-code-exec
A42: Path B - run | B42: B.11 | C42: Long context is generated, not stored. Each length x depth becomes its own row, giving the degradation curve. | D42: python run_api_quality.py --models qwen3-32b --suites long_context --needle-lengths 4000,16000,32000 --needle-depths 0.1,0.5,0.9
A43: Path B - finish | B43: B.12 | C43: Recalculate derived columns. openpyxl writes formulas without cached values. | D43: python recalc_win.py dgx_llm_benchmark.xlsx
A44: Path B - safety net | B44: B.13 | C44: Raw items are flushed to JSONL before Excel is opened, so an interrupted run loses nothing. | D44: results/api_quality_raw-<stamp>.jsonl
A45: PATH C - API, CLOSED MODELS
A46: Path C - purpose | C46: GPT / Claude / Gemini / Grok are absent from the registry by design, and no closed-model runner exists. You do not need one. | D46: Route them through OpenRouter
A47: Path C - setup | B47: C.1 | C47: Add rows to the Models sheet with open_weights=N and a priority. | D47: model_key, display_name, provider, country
A48: Path C - setup | B48: C.2 | C48: Add routes to providers.json. These four ids were live in the OpenRouter catalogue on 31 Jul 2026. | D48: openai/gpt-5.6-sol, anthropic/claude-opus-5, google/gemini-3.6-flash, x-ai/grok-4.5
A49: Path C - setup | B49: C.3 | C49: Every other id is in the 'API ID / Where' column of the Non-Chinese and Chinese sheets of this workbook. | D49: Copy it verbatim
A50: Path C - setup | B50: C.4 | C50: Then the normal commands work unchanged. | D50: python run_api_quality.py --check
A51: Path C - caution | B51: C.5 | C51: Closed models bill per token and --repeats multiplies the bill. Start at 1. | D51: --repeats 1
A52: Path C - first-party | B52: C.6 | C52: OpenAI, xAI and Google's compat endpoint drop into providers.json as-is. | D52: api.openai.com/v1 | api.x.ai/v1 | generativelanguage.googleapis.com/v1beta/openai
A53: Path C - first-party | B53: C.7 | C53: Anthropic does NOT fit as-is: Provider.headers() sends 'Authorization: Bearer', Anthropic wants 'x-api-key' plus 'anthropic-version'. Five-line change, or just use OpenRouter. | D53: run_api_quality.py, Provider.headers()
A54: PATH D - LOCAL DGX
A55: Path D - purpose | C55: The only path that yields real latency, throughput, energy and $/1M-token numbers. | D55: run_ollama_bench.py, then vLLM
A56: Path D - critical | B56: D.1 | C56: Set OLLAMA_NUM_PARALLEL to at least your highest concurrency BEFORE serving. Otherwise you measure queue time and the model looks like it collapsed under load. | D56: export OLLAMA_NUM_PARALLEL=64
A57: Path D - setup | B57: D.2 | C57: Fill Hardware_Env, Run_Config and Cost_Model by hand. Every yellow cell is an input. The Cost_Model placeholders are invented numbers. | D57: Decide SLA thresholds before you see data
A58: Path D - verify | B58: D.3 | C58: Resolve Ollama tags without downloading anything. | D58: python run_ollama_bench.py --check
A59: Path D - run | B59: D.4 | C59: Start small and sanity-check before the full matrix. | D59: python run_ollama_bench.py --models qwen3-32b --concurrency 1,8 --shapes 2048/256 --repeats 1
A60: Path D - run | B60: D.5 | C60: Full sweep. | D60: python run_ollama_bench.py --priority P0 --pull --concurrency 1,4,8,16 --shapes 128/128,2048/256,8192/1024 --repeats 3
A61: Path D - caveat | B61: D.6 | C61: Ollama is llama.cpp: GGUF, layer-split, no tensor parallelism. Expect 20-40% of vLLM on the same weights. Ranks models correctly, under-reports the hardware. | D61: Filter on serving_stack before any chart
A62: Path D - caveat | B62: D.7 | C62: Prompt caching is on, so TTFT after the first request is optimistic. Vary prompts for cold-prefill numbers. | D62: Realistic for chat, wrong for cold start
A63: LATENCY - WHERE IT IS VALID
A64: Latency validity | C64: Web UI: never. You are timing your browser. | D64: Discard
A65: Latency validity | C65: Free API tier: never. You are timing the provider's queue depth. | D65: run_api_quality.py writes no timing columns, by design
A66: Latency validity | C66: Paid API tier: valid IF you will deploy on that API. Streaming on, 3 times of day, repeats >= 5, report p95. | D66: This is what your users will actually feel
A67: Latency validity | C67: DGX with vLLM or TensorRT-LLM: valid for capacity planning and any published number. | D67: The only source for $/1M tokens
A68: READING THE RESULTS
A69: Reading results | B69: R.1 | C69: Read score_ci95_halfwidth BEFORE score_mean. Overlapping intervals mean the models are tied. | D69: More prompts, not more decimal places
A70: Reading results | B70: R.2 | C70: Watch ttft_p95_at_c1_ms - single-user latency with no queueing, what a person in a chat window feels. | D70: Summary sheet
A71: Reading results | B71: R.3 | C71: sla_pass_points is the number for a report: load points meeting BOTH thresholds. Peak throughput at concurrency 128 is meaningless if TTFT was 9 seconds there. | D71: Summary sheet
A72: Reading results | B72: R.4 | C72: A model with no rows in Perf_Results never ran. Check Ollama_Pull_Log. That is not the same as scoring badly. | D72: Ollama_Pull_Log
A73: SUGGESTED FIRST DAY
A74: First day | B74: 1 | C74: git restore . and install dependencies. | D74: ~5 min
A75: First day | B75: 2 | C75: OpenRouter chat: 10 prompts from prompts/reasoning.jsonl against 4 candidates, search off, new chat each time. Cut to 5 models. | D75: ~1 hour
A76: First day | B76: 3 | C76: Get the three keys, run --check, smoke-test one model on one suite. | D76: ~30 min
A77: First day | B77: 4 | C77: Full sweep on the survivors across 5 suites at --repeats 1. | D77: Overnight if needed
A78: First day | B78: 5 | C78: recalc_win.py, then read the confidence intervals first. | D78: ~10 min
A79: First day | B79: 6 | C79: Only then look at latency or fine-tuning, and only for the 2-3 that survived. | D79: Everything else is diagnostic
A81: ADDED 31 JUL 2026
A82: PATH E - QUICK STANDALONE RUNNER (quick_ollama_test.py)
A83: Path E - purpose | C83: Same graders and same prompt format as run_ollama_quality.py, but no workbook, no openpyxl, no sheet_io. Use it to iterate on the DGX before committing to a full campaign. | D83: quick_ollama_test.py
A84: Path E - prereq | B84: E.1 | C84: Restore the repo - it imports graders.py and reads prompts/. | D84: git restore .
A85: Path E - prereq | B85: E.2 | C85: Only dependency beyond the standard library. | D85: pip install httpx
A86: Path E - prereq | B86: E.3 | C86: Set the parallel slot count to at least your concurrency BEFORE serving, or you measure queue time. | D86: export OLLAMA_NUM_PARALLEL=8 && ollama serve
A87: Path E - inspect | B87: E.4 | C87: Show every suite, its prompt count and graders, plus the models installed. Works before you pull anything. | D87: python quick_ollama_test.py --list
A88: Path E - inspect | B88: E.5 | C88: Size a run without touching Ollama at all - deliberately offline. | D88: python quick_ollama_test.py --dry-run --models qwen3:32b
A89: Path E - run | B89: E.6 | C89: Smoke test: 3 prompts per suite, one model. Confirms plumbing in about a minute. | D89: python quick_ollama_test.py --models qwen3:32b --limit 3
A90: Path E - run | B90: E.7 | C90: One suite, one model. | D90: python quick_ollama_test.py --models qwen3:32b --suites reasoning
A91: Path E - run | B91: E.8 | C91: Head-to-head across models. Prints a per-suite table plus a pooled ranking with confidence intervals and a tie verdict. | D91: python quick_ollama_test.py --models qwen3:32b,llama3.3:70b,phi4:14b
A92: Path E - run | B92: E.9 | C92: Coding suite executes model-written Python. Container only. | D92: python quick_ollama_test.py --models qwen3:32b --suites coding --allow-code-exec
A93: Path E - run | B93: E.10 | C93: Repeats and concurrency. Repeats vary the seed, so they measure sampling stability, not grader noise. | D93: python quick_ollama_test.py --models qwen3:32b --repeats 3 --concurrency 8
A94: Path E - run | B94: E.11 | C94: Drive a remote DGX from your laptop. The server needs OLLAMA_HOST=0.0.0.0. | D94: python quick_ollama_test.py --host http://dgx-node:11434 --models qwen3:32b
A95: Path E - output | B95: E.12 | C95: Raw per-item records, flushed as they land - an interrupted run loses nothing. | D95: results/quick_raw-<stamp>.jsonl
... A99: Path E - limits | B99: E.16 | C99: tok/s and prefill come from Ollama's own counters so they are real, but there is no warm-up discipline and prompt caching is on. Smell test only - use run_ollama_bench.py for capacity numbers. | D99: Never quote these as throughput

Sheet Prompts
A1: Test prompts
A2: 174 prompts across 8 suites. Green rows already exist in prompts/*.jsonl; amber rows are new and live in prompts_extra/*.jsonl.
A3: Every expected value was verified by feeding an ideal answer through graders.py - all 68 new prompts score 1.0, so a zero in a real run is the model, not the key. Reference solutions for all 8 new coding prompts were executed against their own unit tests before being written here.
A4: To use the new ones: cat prompts_extra/reasoning.jsonl >> prompts/reasoning.jsonl (or leave them in place - quick_ollama_test.py reads both directories and folds them into the same suite).
A6: ID | B6: Suite | C6: Capability | D6: Grader | E6: Max tokens | F6: System prompt | G6: Prompt | H6: Expected | I6: Tags | J6: Source
A7: REASONING (33 prompts)
A8: rea-001 | B8: reasoning | C8: math_word_problem | D8: numeric | E8: 700 | F8: Solve the problem. End your reply with the final answer as a plain number on its own line. | G8: A warehouse receives 3 pallets holding 48 boxes each. Inspection finds 17 damaged boxes, which are removed. The remaining boxes are divided equally among 5 trucks, and any boxes that do not divide evenly stay behind. How many boxes does each truck carry? | H8: {"answer": 25} | I8: arithmetic, multi_step | J8: existing
A9: rea-002 | B9: reasoning | C9: math_word_problem | D9: numeric | E9: 700 | F9: Solve the problem. End your reply with the final answer as a plain number on its own line. | G9: A tank holds 900 litres and is completely full. A drain removes 15 litres per minute while an inlet adds 9 litres per minute. Both run continuously. How many minutes until the tank is empty? | H9: {"answer": 150} | I9: rates | J9: existing
A10: rea-003 | B10: reasoning | C10: math_word_problem | D10: numeric | E10: 700 | F10: Solve the problem. End your reply with the final answer as a plain number on its own line. | G10: An item is priced at 2400. The price is first increased by 15%, then the new price is reduced by 20%. What is the final price? | H10: {"answer": 2208} | I10: percentages, order_of_operations | J10: existing
A11: rea-004 | B11: reasoning | C11: algebra | D11: numeric | E11: 700 | F11: Solve the problem. End your reply with the final answer as a plain number on its own line. | G11: Anil is currently three times as old as Bala. In eight years, Anil will be twice as old as Bala. How old is Bala now? | H11: {"answer": 8} | I11: algebra | J11: existing
A12: rea-005 | B12: reasoning | C12: math_word_problem | D12: numeric | E12: 700 | F12: Solve the problem. End your reply with the final answer as a plain number on its own line. | G12: Worker A completes a job alone in 12 days. Worker B completes the same job alone in 18 days. Working together at those rates, how many days do they take? Give the answer as a decimal. | H12: {"answer": 7.2, "tolerance": 0.01} | I12: rates, fractions | J12: existing
A13: rea-006 | B13: reasoning | C13: arithmetic | D13: numeric | E13: 700 | F13: Solve the problem. End your reply with the final answer as a plain number on its own line. | G13: The mean of six numbers is 24. One of the numbers, 39, is removed. What is the mean of the five numbers that remain? | H13: {"answer": 21} | I13: statistics | J13: existing
A14: rea-007 | B14: reasoning | C14: geometry | D14: numeric | E14: 700 | F14: Solve the problem. End your reply with the final answer as a plain number on its own line. | G14: A rectangle has a perimeter of 46 cm. Its length is 4 cm greater than its width. What is its area in square centimetres? | H14: {"answer": 128.25, "tolerance": 0.01} | I14: geometry | J14: existing
A15: rea-008 | B15: reasoning | C15: number_theory | D15: numeric | E15: 700 | F15: Solve the problem. End your reply with the final answer as a plain number on its own line. | G15: What is the smallest three-digit whole number that is divisible by both 6 and 8? | H15: {"answer": 120} | I15: number_theory | J15: existing
A16: rea-009 | B16: reasoning | C16: pattern | D16: numeric | E16: 700 | F16: Solve the problem. End your reply with the final answer as a plain number on its own line. | G16: A sequence begins 3, 7, 15, 31, 63. Each term follows the same rule applied to the previous term. What is the next term? | H16: {"answer": 127} | I16: sequences | J16: existing
A17: rea-010 | B17: reasoning | C17: combinatorics | D17: numeric | E17: 700 | F17: Solve the problem. End your reply with the final answer as a plain number on its own line. | G17: Nine people attend a meeting. Every person shakes hands exactly once with every other person. How many handshakes take place in total? | H17: {"answer": 36} | I17: combinatorics | J17: existing
A18: rea-011 | B18: reasoning | C18: logic | D18: numeric | E18: 900 | F18: Reason carefully. End your reply with the final answer as a plain number on its own line. | G18: Five people are in a room. Each is either a knight, who always tells the truth, or a knave, who always lies. Person 1 says 'exactly one of us is a knave'. Person 2 says 'exactly two of us are knaves'. Person 3 says 'exactly three of us are knaves'. Person 4 says 'exactly four of us are knaves'. Person 5 says 'exactly five of us are knaves'. How many knaves are in the room? | H18: {"answer": 4} | I18: logic, self_reference | J18: existing
A19: rea-012 | B19: reasoning | C19: math_word_problem | D19: numeric | E19: 700 | F19: Solve the problem. End your reply with the final answer as a plain number on its own line. | G19: A shopkeeper buys 12 pens for a total of 216 and sells each pen for 25. What is the total profit on all 12 pens? | H19: {"answer": 84} | I19: arithmetic | J19: existing
... A40: rea-033 | B40: reasoning | C40: logic | D40: exact_match | E40: 500 | F40: Solve the problem. Reply with the answer alone, no explanation. | G40: A deployment runs every 6 hours starting at 00:00. A backup runs every 8 hours starting at 00:00. At what time do they next coincide after 00:00? Answer in 24-hour HH:MM format. | H40: {"any_of": ["24:00", "00:00"]} | I40: scheduling, lcm | J40: NEW - 31 Jul 2026
A41: KNOWLEDGE (27 prompts)
A42: knw-001 | B42: knowledge | C42: science | D42: multiple_choice | E42: 50 | F42: Answer with a single letter: A, B, C or D. No explanation. | G42: Which gas makes up the largest proportion of Earth's atmosphere by volume? A) Oxygen B) Nitrogen C) Carbon dioxide D) Argon | H42: {"answer": "B"} | I42: chemistry | J42: existing
A43: knw-002 | B43: knowledge | C43: computing | D43: multiple_choice | E43: 50 | F43: Answer with a single letter: A, B, C or D. No explanation. | G43: In Big-O notation, what is the average time complexity of a lookup in a well-distributed hash table? A) O(n) B) O(log n) C) O(1) D) O(n log n) | H43: {"answer": "C"} | I43: algorithms | J43: existing
A44: knw-003 | B44: knowledge | C44: computing | D44: multiple_choice | E44: 50 | F44: Answer with a single letter: A, B, C or D. No explanation. | G44: Which layer of the OSI model does TCP operate at? A) Network B) Transport C) Session D) Data link | H44: {"answer": "B"} | I44: networking | J44: existing
A45: knw-004 | B45: knowledge | C45: science | D45: multiple_choice | E45: 50 | F45: Answer with a single letter: A, B, C or D. No explanation. | G45: What is the powerhouse organelle of a eukaryotic cell, where most ATP is produced? A) Ribosome B) Golgi apparatus C) Mitochondrion D) Lysosome | H45: {"answer": "C"} | I45: biology | J45: existing
A46: knw-005 | B46: knowledge | C46: geography | D46: multiple_choice | E46: 50 | F46: Answer with a single letter: A, B, C or D. No explanation. | G46: Which of these countries does NOT share a land border with India? A) Bhutan B) Nepal C) Sri Lanka D) Bangladesh | H46: {"answer": "C"} | I46: geography, negation | J46: existing
A47: knw-006 | B47: knowledge | C47: computing | D47: multiple_choice | E47: 50 | F47: Answer with a single letter: A, B, C or D. No explanation. | G47: In a relational database, what does the ACID acronym's 'D' stand for? A) Distribution B) Durability C) Determinism D) Delegation | H47: {"answer": "B"} | I47: databases | J47: existing
A48: knw-007 | B48: knowledge | C48: physics | D48: multiple_choice | E48: 50 | F48: Answer with a single letter: A, B, C or D. No explanation. | G48: What is the approximate speed of light in a vacuum? A) 300 km/s B) 3,000 km/s C) 300,000 km/s D) 3,000,000 km/s | H48: {"answer": "C"} | I48: physics | J48: existing
A49: knw-008 | B49: knowledge | C49: computing | D49: multiple_choice | E49: 50 | F49: Answer with a single letter: A, B, C or D. No explanation. | G49: Which data structure operates on a last-in, first-out basis? A) Queue B) Stack C) Linked list D) Heap | H49: {"answer": "B"} | I49: data_structures | J49: existing
A50: knw-009 | B50: knowledge | C50: history | D50: multiple_choice | E50: 50 | F50: Answer with a single letter: A, B, C or D. No explanation. | G50: In which year did the Second World War end in Europe? A) 1943 B) 1944 C) 1945 D) 1946 | H50: {"answer": "C"} | I50: history | J50: existing
A51: knw-010 | B51: knowledge | C51: computing | D51: multiple_choice | E51: 50 | F51: Answer with a single letter: A, B, C or D. No explanation. | G51: What does a GPU's HBM refer to? A) High Bandwidth Memory B) Hybrid Buffer Module C) Hierarchical Block Mapping D) Host Bus Manager | H51: {"answer": "A"} | I51: hardware | J51: existing
A52: knw-011 | B52: knowledge | C52: mathematics | D52: multiple_choice | E52: 50 | F52: Answer with a single letter: A, B, C or D. No explanation. | G52: Which of these numbers is prime? A) 91 B) 87 C) 97 D) 99 | H52: {"answer": "C"} | I52: number_theory | J52: existing
A53: knw-012 | B53: knowledge | C53: computing | D53: multiple_choice | E53: 50 | F53: Answer with a single letter: A, B, C or D. No explanation. | G53: In machine learning, what does the 'attention' mechanism in a transformer primarily compute? A) A convolution over fixed-size windows B) Weighted relationships between all positions in a sequence C) A recurrent hidden state passed left to right D) A fixed positional embedding lookup | H53: {"answer": "B"} | I53: ml | J53: existing
... A68: knw-027 | B68: knowledge | C68: computing | D68: multiple_choice | E68: 50 | F68: Answer with a single letter: A, B, C or D. No explanation. | G68: Which quantization format stores each weight in 4 bits? A) BF16 B) FP8 C) INT4-AWQ D) FP32 | H68: {"answer": "C"} | I68: llm_infra | J68: NEW - 31 Jul 2026
A69: CODING (18 prompts)
A70: cod-001 | B70: coding | C70: code_generation | D70: code_exec | E70: 900 | F70: Write Python only. Output a single code block containing the complete function and nothing else. Do not include example usage or tests. | G70: Write a function `run_length_encode(s: str) -> str` that compresses a string by replacing runs of the same character with the character followed by the run length. Runs of length 1 keep the count. For example 'aaabbc' becomes 'a3b2c1'. An empty string returns an empty string. | H70: {"tests": "assert run_length_encode('aaabbc') == 'a3b2c1'\nassert run_length_encode('') == ''\nassert run_length_encode('x') == 'x1'\nassert run_length_encode('aabbaa') == 'a2b2a2'"} | I70: strings | J70: existing
A71: cod-002 | B71: coding | C71: code_generation | D71: code_exec | E71: 900 | F71: Write Python only. Output a single code block containing the complete function and nothing else. Do not include example usage or tests. | G71: Write a function `merge_intervals(intervals: list) -> list` that takes a list of [start, end] pairs and returns them merged and sorted by start, with overlapping or touching intervals combined. For example [[1,3],[2,6],[8,10]] returns [[1,6],[8,10]]. | H71: {"tests": "assert merge_intervals([[1,3],[2,6],[8,10]]) == [[1,6],[8,10]]\nassert merge_intervals([]) == []\nassert merge_intervals([[5,7],[1,2]]) == [[1,2],[5,7]]\nassert merge_intervals([[1,4],[4,5]]) == [[1,5]]"} | I71: algorithms | J71: existing
A72: cod-003 | B72: coding | C72: code_generation | D72: code_exec | E72: 900 | F72: Write Python only. Output a single code block containing the complete function and nothing else. Do not include example usage or tests. | G72: Write a function `is_balanced(s: str) -> bool` that returns True if every bracket in the string is correctly matched and nested. Consider round, square and curly brackets. Any other character is ignored. | H72: {"tests": "assert is_balanced('(a[b]{c})') is True\nassert is_balanced('([)]') is False\nassert is_balanced('') is True\nassert is_balanced('(((') is False\nassert is_balanced('no brackets here') is True"} | I72: stacks | J72: existing
A73: cod-004 | B73: coding | C73: code_generation | D73: code_exec | E73: 900 | F73: Write Python only. Output a single code block containing the complete function and nothing else. Do not include example usage or tests. | G73: Write a function `top_k_frequent(words: list, k: int) -> list` that returns the k most frequent words, ordered by descending count and, where counts tie, alphabetically ascending. | H73: {"tests": "assert top_k_frequent(['b','a','b','c','a','b'], 2) == ['b','a']\nassert top_k_frequent(['x','y'], 2) == ['x','y']\nassert top_k_frequent(['same','same','tie','tie','z'], 2) == ['same','tie']\nassert top_k_frequent([], 3) == []"} | I73: sorting, tie_breaking | J73: existing
A74: cod-005 | B74: coding | C74: code_generation | D74: code_exec | E74: 900 | F74: Write Python only. Output a single code block containing the complete function and nothing else. Do not include example usage or tests. | G74: Write a function `flatten(nested: list) -> list` that flattens an arbitrarily nested list of integers into a single flat list, preserving order. | H74: {"tests": "assert flatten([1,[2,[3,4]],5]) == [1,2,3,4,5]\nassert flatten([]) == []\nassert flatten([[[[7]]]]) == [7]\nassert flatten([1,[],2]) == [1,2]"} | I74: recursion | J74: existing
A75: cod-006 | B75: coding | C75: code_generation | D75: code_exec | E75: 900 | F75: Write Python only. Output a single code block containing the complete function and nothing else. Do not include example usage or tests. | G75: Write a function `parse_duration(text: str) -> int` that converts a duration string such as '1h30m', '45m', '2h' or '90s' into a total number of seconds. Supported units are h, m and s. Return 0 for an empty string. | H75: {"tests": "assert parse_duration('1h30m') == 5400\nassert parse_duration('45m') == 2700\nassert parse_duration('2h') == 7200\nassert parse_duration('90s') == 90\nassert parse_duration('') == 0\nassert parse_duration('1h1m1s') == 3661"} | I75: parsing | J75: existing
A76: cod-007 | B76: coding | C76: code_generation | D76: code_exec | E76: 900 | F76: Write Python only. Output a single code block containing the complete function and nothing else. Do not include example usage or tests. | G76: Write a function `chunk_by_size(items: list, max_size: int) -> list` that splits a list into consecutive chunks of at most max_size items each. The final chunk may be shorter. Raise ValueError if max_size is less than 1. | H76: {"tests": "assert chunk_by_size([1,2,3,4,5], 2) == [[1,2],[3,4],[5]]\nassert chunk_by_size([], 3) == []\nassert chunk_by_size([1,2,3], 5) == [[1,2,3]]\ntry:\n chunk_by_size([1], 0)\n raise AssertionError('expected ValueError')\nexcept ValueError:\n pass"} | I76: edge_cases, exceptions | J76: existing
A77: cod-008 | B77: coding | C77: code_generation | D77: code_exec | E77: 900 | F77: Write Python only. Output a single code block containing the complete function and nothing else. Do not include example usage or tests. | G77: Write a function `normalise_whitespace(s: str) -> str` that collapses every run of whitespace, including tabs and newlines, into a single space, and strips leading and trailing whitespace. | H77: {"tests": "assert normalise_whitespace(' a\\t\\tb\\n c ') == 'a b c'\nassert normalise_whitespace('') == ''\nassert normalise_whitespace(' ') == ''\nassert normalise_whitespace('one') == 'one'"} | I77: strings | J77: existing
A78: cod-009 | B78: coding | C78: code_generation | D78: code_exec | E78: 900 | F78: Write Python only. Output a single code block containing the complete function and nothing else. Do not include example usage or tests. | G78: Write a function `moving_average(values: list, window: int) -> list` that returns the simple moving average over the given window size. The result has len(values) - window + 1 entries. Return an empty list if the window is larger than the input. | H78: {"tests": "assert moving_average([1,2,3,4], 2) == [1.5, 2.5, 3.5]\nassert moving_average([1,2], 5) == []\nassert moving_average([2,2,2], 3) == [2.0]\nassert moving_average([], 2) == []"} | I78: numeric | J78: existing
A79: cod-010 | B79: coding | C79: bug_fixing | D79: code_exec | E79: 900 | F79: Write Python only. Output a single code block containing the complete corrected function and nothing else. Do not include example usage or tests. | G79: This function is meant to return the second largest distinct value in a list, or None if there are fewer than two distinct values. It is wrong. Return a corrected version with the same name. def second_largest(nums): nums.sort() return nums[-2] | H79: {"tests": "assert second_largest([3,1,4,4,2]) == 3\nassert second_largest([5]) is None\nassert second_largest([7,7,7]) is None\nassert second_largest([1,2]) == 1\noriginal = [9,1,5]\nsecond_largest(original)\nassert original == [9,1,5], 'must not mutate the caller list'"} | I79: debugging, side_effects | J79: existing
A80: cod-011 | B80: coding | C80: code_generation | D80: code_exec | E80: 900 | F80: Write Python only. Output a single code block containing the complete function and nothing else. Do not include example usage or tests. | G80: Write a function `dedupe_preserve_order(items: list) -> list` that removes duplicates from a list while keeping the first occurrence of each element in its original position. | H80: {"tests": "assert dedupe_preserve_order([1,2,1,3,2]) == [1,2,3]\nassert dedupe_preserve_order([]) == []\nassert dedupe_preserve_order(['a','a','a']) == ['a']\nassert dedupe_preserve_order([3,1,2]) == [3,1,2]"} | I80: lists | J80: NEW - 31 Jul 2026
A81: cod-012 | B81: coding | C81: code_generation | D81: code_exec | E81: 900 | F81: Write Python only. Output a single code block containing the complete function and nothing else. Do not include example usage or tests. | G81: Write a function `is_valid_ipv4(s: str) -> bool` that returns True only if the string is a valid dotted-quad IPv4 address: exactly four parts, each an integer from 0 to 255, with no leading zeros unless the part is exactly '0'. | H81: {"tests": "assert is_valid_ipv4('192.168.0.1') is True\nassert is_valid_ipv4('256.1.1.1') is False\nassert is_valid_ipv4('01.2.3.4') is False\nassert is_valid_ipv4('1.2.3') is False\nassert is_valid_ipv4('0.0.0.0') is True"} | I81: validation | J81: NEW - 31 Jul 2026
... A87: cod-018 | B87: coding | C87: code_generation | D87: code_exec | E87: 900 | F87: Write Python only. Output a single code block containing the complete function and nothing else. Do not include example usage or tests. | G87: Write a function `count_tokens_per_second(tokens: int, seconds: float) -> float` that returns tokens divided by seconds, rounded to two decimal places. If seconds is zero, return 0.0 rather than raising. | H87: {"tests": "assert count_tokens_per_second(850, 21.25) == 40.0\nassert count_tokens_per_second(100, 0) == 0.0\nassert count_tokens_per_second(1, 3) == 0.33"} | I87: guard_clause | J87: NEW - 31 Jul 2026
A88: INSTRUCTION_FOLLOWING (25 prompts)
A89: ifl-001 | B89: instruction_following | C89: constraint_adherence | D89: constraint_check | E89: 400 | F89: Follow every formatting instruction exactly. Output only what is asked for. | G89: List exactly four benefits of automated testing. Use a hyphen bullet for each one. Do not write any introduction or closing line. | H89: {"constraints": {"bullet_count": 4, "max_words": 90}} | I89: bullets | J89: existing
A90: ifl-002 | B90: instruction_following | C90: constraint_adherence | D90: constraint_check | E90: 300 | F90: Follow every formatting instruction exactly. Output only what is asked for. | G90: Describe what a database index does, in exactly one sentence of 25 words or fewer. Do not use the word 'data'. | H90: {"constraints": {"sentence_count": 1, "max_words": 25, "forbid_word": "data"}} | I90: length, forbidden_word | J90: existing
A91: ifl-003 | B91: instruction_following | C91: constraint_adherence | D91: constraint_check | E91: 200 | F91: Follow every formatting instruction exactly. Output only what is asked for. | G91: Write a single line of text that begins with the word BEGIN and ends with the word END. Put exactly three words between them. | H91: {"constraints": {"line_count": 1, "starts_with": "BEGIN", "ends_with": "END", "exact_words": 5}} | I91: anchoring | J91: existing
A92: ifl-004 | B92: instruction_following | C92: constraint_adherence | D92: constraint_check | E92: 200 | F92: Follow every formatting instruction exactly. Output only what is asked for. | G92: Reply with the names of three programming languages, all in lowercase, separated by commas, with no other text and no full stop. | H92: {"constraints": {"all_lowercase": true, "no_punctuation": false, "max_words": 8, "contains_none": ["."]}} | I92: casing | J92: existing
A93: ifl-005 | B93: instruction_following | C93: constraint_adherence | D93: constraint_check | E93: 500 | F93: Follow every formatting instruction exactly. Output only what is asked for. | G93: Summarise why version control matters. Your answer must be at least 60 words and must include all three of these terms: history, branch, rollback. | H93: {"constraints": {"min_words": 60, "contains_all": ["history", "branch", "rollback"]}} | I93: inclusion, min_length | J93: existing
A94: ifl-006 | B94: instruction_following | C94: constraint_adherence | D94: constraint_check | E94: 200 | F94: Follow every formatting instruction exactly. Output only what is asked for. | G94: Name one advantage of caching. Write your entire answer in capital letters, with no punctuation at all. | H94: {"constraints": {"all_uppercase": true, "no_punctuation": true, "max_words": 30}} | I94: casing, punctuation | J94: existing
A95: ifl-007 | B95: instruction_following | C95: constraint_adherence | D95: constraint_check | E95: 400 | F95: Follow every formatting instruction exactly. Output only what is asked for. | G95: Explain what a load balancer does, in exactly two sentences. Neither sentence may contain the word 'traffic'. | H95: {"constraints": {"sentence_count": 2, "forbid_word": "traffic"}} | I95: forbidden_word, sentence_count | J95: existing
A96: ifl-008 | B96: instruction_following | C96: constraint_adherence | D96: constraint_check | E96: 200 | F96: Follow every formatting instruction exactly. Output only what is asked for. | G96: Output exactly five lines. Each line must contain a single number, counting down from 5 to 1. No other characters on any line. | H96: {"constraints": {"line_count": 5, "matches_regex": "^\\s*5\\s*\\n\\s*4\\s*\\n\\s*3\\s*\\n\\s*2\\s*\\n\\s*1\\s*$"}} | I96: exact_output | J96: existing
A97: ifl-009 | B97: instruction_following | C97: constraint_adherence | D97: constraint_check | E97: 100 | F97: Follow every formatting instruction exactly. Output only what is asked for. | G97: Answer with one word only: what protocol does HTTPS use to encrypt traffic? | H97: {"constraints": {"exact_words": 1, "contains_all": ["TLS"]}} | I97: single_word | J97: existing
A98: ifl-010 | B98: instruction_following | C98: constraint_adherence | D98: constraint_check | E98: 300 | F98: Follow every formatting instruction exactly. Output only what is asked for. | G98: Write three bullet points about API rate limiting. Every bullet must start with a hyphen and every bullet must be under 12 words. Add no heading and no closing remark. | H98: {"constraints": {"bullet_count": 3, "max_words": 40}} | I98: bullets, length | J98: existing
A99: ifl-011 | B99: instruction_following | C99: constraint_adherence | D99: constraint_check | E99: 200 | F99: Follow every formatting instruction exactly. Output only what is asked for. | G99: Reply with valid JSON only, no prose and no code fence, containing a single key called status whose value is the string ok. | H99: {"constraints": {"is_json": true, "contains_all": ["status", "ok"], "max_words": 10}} | I99: json, no_prose | J99: existing
A100: ifl-012 | B100: instruction_following | C100: constraint_adherence | D100: constraint_check | E100: 300 | F100: Follow every formatting instruction exactly. Output only what is asked for. | G100: Describe the purpose of a firewall in 40 words or fewer. Do not mention the words 'network' or 'security'. | H100: {"constraints": {"max_words": 40, "contains_none": ["network", "security"]}} | I100: forbidden_word, length | J100: existing
... A113: ifl-025 | B113: instruction_following | C113: constraint_adherence | D113: constraint_check | E113: 500 | F113: Follow every formatting instruction exactly. Output only what is asked for. | G113: Explain database sharding in at least 40 words but no more than 60 words. Write it as a single paragraph with no bullets. | H113: {"constraints": {"min_words": 40, "max_words": 60, "bullet_count": 0}} | I113: range_length | J113: NEW - 31 Jul 2026
A114: STRUCTURED_OUTPUT (19 prompts)
A115: jsn-001 | B115: structured_output | C115: json_extraction | D115: json_schema | E115: 400 | F115: Reply with a single valid JSON object and nothing else. No prose, no code fence. | G115: Extract the fields from this line into JSON with keys name, email and total. Invoice for Priya Raman (priya.raman@example.com), amount due 4820.50 | H115: {"schema": {"type": "object", "required": ["name", "email", "total"], "properties": {"name": {"type": "string"}, "email": {"type": "string"}, "total": {"type": "number"}}}, "values": {"email": "priya.raman@example.com"}} | I115: extraction | J115: existing
A116: jsn-002 | B116: structured_output | C116: json_typing | D116: json_schema | E116: 400 | F116: Reply with a single valid JSON object and nothing else. No prose, no code fence. | G116: Return JSON with keys hostname (string), port (integer) and tls_enabled (boolean) describing this connection string: db-prod-02:5432 with TLS turned on. | H116: {"schema": {"type": "object", "required": ["hostname", "port", "tls_enabled"], "properties": {"hostname": {"type": "string"}, "port": {"type": "integer"}, "tls_enabled": {"type": "boolean"}}}, "values": {"hostname": "db-prod-02", "port": 5432}} | I116: types | J116: existing
A117: jsn-003 | B117: structured_output | C117: json_array | D117: json_schema | E117: 400 | F117: Reply with a single valid JSON object and nothing else. No prose, no code fence. | G117: Return JSON with one key, items, whose value is an array of the three product names in this sentence: We stock keyboards, monitors and docking stations. | H117: {"schema": {"type": "object", "required": ["items"], "properties": {"items": {"type": "array", "minItems": 3, "items": {"type": "string"}}}}} | I117: arrays | J117: existing
A118: jsn-004 | B118: structured_output | C118: json_enum | D118: json_schema | E118: 400 | F118: Reply with a single valid JSON object and nothing else. No prose, no code fence. | G118: Classify the sentiment of this review as one of: positive, negative, neutral. Return JSON with keys sentiment and confidence (a number between 0 and 1). Review: The delivery arrived two days late and the box was crushed. | H118: {"schema": {"type": "object", "required": ["sentiment", "confidence"], "properties": {"sentiment": {"type": "string", "enum": ["positive", "negative", "neutral"]}, "confidence": {"type": "number"}}}, "values": {"sentiment": "negative"}} | I118: enum, classification | J118: existing
A119: jsn-005 | B119: structured_output | C119: json_nested | D119: json_schema | E119: 400 | F119: Reply with a single valid JSON object and nothing else. No prose, no code fence. | G119: Return JSON with keys order_id (string) and customer, where customer is an object with keys first_name and last_name. Source: Order A-7741 was placed by Rahul Menon. | H119: {"schema": {"type": "object", "required": ["order_id", "customer"], "properties": {"order_id": {"type": "string"}, "customer": {"type": "object", "required": ["first_name", "last_name"], "properties": {"first_name": {"type": "string"}, "last_name": {"type": "string"}}}}}} | I119: nesting | J119: existing
A120: jsn-006 | B120: structured_output | C120: json_null_handling | D120: json_schema | E120: 400 | F120: Reply with a single valid JSON object and nothing else. No prose, no code fence. | G120: Extract name, email and phone into JSON. If a field is absent from the text, set it to null rather than inventing a value. Contact: Sana Iqbal, reachable at sana.iqbal@example.org | H120: {"schema": {"type": "object", "required": ["name", "email", "phone"]}, "values": {"email": "sana.iqbal@example.org"}} | I120: missing_fields, hallucination_resistance | J120: existing
A121: jsn-007 | B121: structured_output | C121: json_array_objects | D121: json_schema | E121: 600 | F121: Reply with a single valid JSON object and nothing else. No prose, no code fence. | G121: Return JSON with a key rows holding an array of objects, each with keys city and population (integer). Pune 7400000, Kochi 2100000, Surat 6900000 | H121: {"schema": {"type": "object", "required": ["rows"], "properties": {"rows": {"type": "array", "minItems": 3, "items": {"type": "object", "required": ["city", "population"], "properties": {"city": {"type": "string"}, "population": {"type": "integer"}}}}}}} | I121: tabular | J121: existing
A122: jsn-008 | B122: structured_output | C122: json_escaping | D122: json_schema | E122: 300 | F122: Reply with a single valid JSON object and nothing else. No prose, no code fence. | G122: Return JSON with a single key message whose value is exactly this text, correctly escaped: He said "stop" and left. | H122: {"schema": {"type": "object", "required": ["message"], "properties": {"message": {"type": "string"}}}} | I122: escaping | J122: existing
A123: jsn-009 | B123: structured_output | C123: json_date | D123: json_schema | E123: 300 | F123: Reply with a single valid JSON object and nothing else. No prose, no code fence. | G123: Return JSON with keys event and date, where date is in ISO 8601 YYYY-MM-DD form. Source: The audit is scheduled for 3 March 2027. | H123: {"schema": {"type": "object", "required": ["event", "date"], "properties": {"event": {"type": "string"}, "date": {"type": "string"}}}, "values": {"date": "2027-03-03"}} | I123: date_format | J123: existing
A124: jsn-010 | B124: structured_output | C124: json_numeric | D124: json_schema | E124: 400 | F124: Reply with a single valid JSON object and nothing else. No prose, no code fence. | G124: Compute the total and return JSON with keys subtotal, tax and total as numbers. Subtotal is 1200, tax is 18 percent of the subtotal. | H124: {"schema": {"type": "object", "required": ["subtotal", "tax", "total"], "properties": {"subtotal": {"type": "number"}, "tax": {"type": "number"}, "total": {"type": "number"}}}, "values": {"tax": 216, "total": 1416}} | I124: computation | J124: existing
A125: jsn-011 | B125: structured_output | C125: json_boolean_logic | D125: json_schema | E125: 300 | F125: Reply with a single valid JSON object and nothing else. No prose, no code fence. | G125: Return JSON with keys in_stock (boolean) and quantity (integer) for this record: Item SKU-9912, 0 units remaining in the warehouse. | H125: {"schema": {"type": "object", "required": ["in_stock", "quantity"], "properties": {"in_stock": {"type": "boolean"}, "quantity": {"type": "integer"}}}, "values": {"quantity": 0}} | I125: inference | J125: existing
A126: jsn-012 | B126: structured_output | C126: json_no_prose | D126: json_schema | E126: 300 | F126: Reply with a single valid JSON object and nothing else. No prose, no code fence. | G126: Return JSON with keys language and paradigm for: Haskell. | H126: {"schema": {"type": "object", "required": ["language", "paradigm"], "properties": {"language": {"type": "string"}, "paradigm": {"type": "string"}}}, "values": {"language": "Haskell"}} | I126: simple | J126: existing
... A133: jsn-019 | B133: structured_output | C133: json_generation | D133: json_schema | E133: 400 | F133: Reply with a single valid JSON object and nothing else. No prose, no code fence. | G133: Return JSON with keys name (string) and tags (array of strings) for: the model qwen3-32b is tagged dense and multilingual. | H133: {"schema": {"type": "object", "required": ["name", "tags"], "properties": {"name": {"type": "string"}, "tags": {"type": "array", "minItems": 2, "items": {"type": "string"}}}}, "values": {"name": "qwen3-32b"}} | I133: arrays | J133: NEW - 31 Jul 2026
A134: TOOL_CALLING (17 prompts)
A135: tol-001 | B135: tool_calling | C135: tool_selection | D135: tool_call | E135: 300 | F135: You have these tools: - get_weather(city: string, unit: string) - send_email(to: string, subject: string, body: string) - create_ticket(title: string, priority: string) Reply with a single JSON object of the form {"name": <tool>, "arguments": {...}} and nothing else. | G135: What is the temperature in Chennai right now, in celsius? | H135: {"tool": "get_weather", "arguments": {"city": "Chennai", "unit": "celsius"}} | I135: single_tool | J135: existing
A136: tol-002 | B136: tool_calling | C136: tool_selection | D136: tool_call | E136: 300 | F136: You have these tools: - get_weather(city: string, unit: string) - send_email(to: string, subject: string, body: string) - create_ticket(title: string, priority: string) Reply with a single JSON object of the form {"name": <tool>, "arguments": {...}} and nothing else. | G136: Raise a high priority ticket titled Database connection pool exhausted. | H136: {"tool": "create_ticket", "arguments": {"title": "Database connection pool exhausted", "priority": "high"}} | I136: single_tool | J136: existing
A137: tol-003 | B137: tool_calling | C137: tool_selection | D137: tool_call | E137: 300 | F137: You have these tools: - search_orders(customer_id: string, status: string) - refund_order(order_id: string, amount: number) - cancel_order(order_id: string) Reply with a single JSON object of the form {"name": <tool>, "arguments": {...}} and nothing else. | G137: Cancel order number ORD-5512. | H137: {"tool": "cancel_order", "arguments": {"order_id": "ORD-5512"}} | I137: argument_extraction | J137: existing
A138: tol-004 | B138: tool_calling | C138: argument_typing | D138: tool_call | E138: 300 | F138: You have these tools: - search_orders(customer_id: string, status: string) - refund_order(order_id: string, amount: number) - cancel_order(order_id: string) Reply with a single JSON object of the form {"name": <tool>, "arguments": {...}} and nothing else. | G138: Refund 249.99 against order ORD-8830. | H138: {"tool": "refund_order", "arguments": {"order_id": "ORD-8830", "amount": 249.99}} | I138: numeric_argument | J138: existing
A139: tol-005 | B139: tool_calling | C139: tool_selection | D139: tool_call | E139: 300 | F139: You have these tools: - search_orders(customer_id: string, status: string) - refund_order(order_id: string, amount: number) - cancel_order(order_id: string) Reply with a single JSON object of the form {"name": <tool>, "arguments": {...}} and nothing else. | G139: Show me every pending order for customer CUST-114. | H139: {"tool": "search_orders", "arguments": {"customer_id": "CUST-114", "status": "pending"}} | I139: two_arguments | J139: existing
A140: tol-006 | B140: tool_calling | C140: distractor_resistance | D140: tool_call | E140: 300 | F140: You have these tools: - convert_currency(amount: number, from: string, to: string) - get_exchange_rate(from: string, to: string) - list_currencies() Reply with a single JSON object of the form {"name": <tool>, "arguments": {...}} and nothing else. | G140: What is the current rate between USD and INR? I do not need a conversion, just the rate. | H140: {"tool": "get_exchange_rate", "arguments": {"from": "USD", "to": "INR"}} | I140: near_miss_tools | J140: existing
A141: tol-007 | B141: tool_calling | C141: distractor_resistance | D141: tool_call | E141: 300 | F141: You have these tools: - convert_currency(amount: number, from: string, to: string) - get_exchange_rate(from: string, to: string) - list_currencies() Reply with a single JSON object of the form {"name": <tool>, "arguments": {...}} and nothing else. | G141: Convert 500 euros into Japanese yen. | H141: {"tool": "convert_currency", "arguments": {"amount": 500, "from": "EUR", "to": "JPY"}} | I141: normalisation | J141: existing
A142: tol-008 | B142: tool_calling | C142: no_argument_tool | D142: tool_call | E142: 300 | F142: You have these tools: - convert_currency(amount: number, from: string, to: string) - get_exchange_rate(from: string, to: string) - list_currencies() Reply with a single JSON object of the form {"name": <tool>, "arguments": {...}} and nothing else. | G142: Which currencies do you support? | H142: {"tool": "list_currencies", "arguments": {}} | I142: empty_arguments | J142: existing
A143: tol-009 | B143: tool_calling | C143: argument_extraction | D143: tool_call | E143: 300 | F143: You have these tools: - schedule_meeting(title: string, date: string, duration_minutes: integer) - cancel_meeting(meeting_id: string) - find_free_slot(date: string, duration_minutes: integer) Reply with a single JSON object of the form {"name": <tool>, "arguments": {...}} and nothing else. Dates must be ISO 8601 YYYY-MM-DD. | G143: Book a 45 minute meeting called Sprint review on 12 October 2027. | H143: {"tool": "schedule_meeting", "arguments": {"title": "Sprint review", "date": "2027-10-12", "duration_minutes": 45}} | I143: date_normalisation | J143: existing
A144: tol-010 | B144: tool_calling | C144: tool_selection | D144: tool_call | E144: 300 | F144: You have these tools: - schedule_meeting(title: string, date: string, duration_minutes: integer) - cancel_meeting(meeting_id: string) - find_free_slot(date: string, duration_minutes: integer) Reply with a single JSON object of the form {"name": <tool>, "arguments": {...}} and nothing else. Dates must be ISO 8601 YYYY-MM-DD. | G144: When am I free for 30 minutes on 2027-01-08? | H144: {"tool": "find_free_slot", "arguments": {"date": "2027-01-08", "duration_minutes": 30}} | I144: single_tool | J144: existing
A145: tol-011 | B145: tool_calling | C145: argument_extraction | D145: tool_call | E145: 300 | F145: You have these tools: - query_database(table: string, filter: string) - export_csv(table: string, path: string) - drop_table(table: string) Reply with a single JSON object of the form {"name": <tool>, "arguments": {...}} and nothing else. | G145: Export the invoices table to /tmp/invoices.csv | H145: {"tool": "export_csv", "arguments": {"table": "invoices", "path": "/tmp/invoices.csv"}} | I145: path_argument | J145: existing
A146: tol-012 | B146: tool_calling | C146: distractor_resistance | D146: tool_call | E146: 300 | F146: You have these tools: - query_database(table: string, filter: string) - export_csv(table: string, path: string) - drop_table(table: string) Reply with a single JSON object of the form {"name": <tool>, "arguments": {...}} and nothing else. | G146: Find all rows in the customers table where country is Japan. | H146: {"tool": "query_database", "arguments": {"table": "customers", "filter": null}} | I146: dangerous_neighbour | J146: existing
... A151: tol-017 | B151: tool_calling | C151: tool_selection | D151: tool_call | E151: 300 | F151: You have these tools: - get_weather(city: string, unit: string) - send_email(to: string, subject: string, body: string) - create_ticket(title: string, priority: string) - search_logs(service: string, level: string, since: string) - restart_service(name: string, force: boolean) Reply with a single JSON object of the form {"name": <tool>, "arguments": {...}} and nothing else. | G151: Open a low priority ticket called Update runbook for cache eviction. | H151: {"tool": "create_ticket", "arguments": {"title": "Update runbook for cache eviction", "priority": "low"}} | I151: single_tool | J151: NEW - 31 Jul 2026
A152: EXTRACTION (20 prompts)
A153: ext-001 | B153: extraction | C153: grounded_qa | D153: exact_match | E153: 100 | F153: Answer using only the passage provided. Reply with the answer alone, no explanation. | G153: Passage: The Meridian substation was commissioned in March 2019 and operates at 132 kV. It supplies four districts and was upgraded in 2023 with a second transformer rated at 40 MVA. Question: What is the rating of the transformer added in 2023? | H153: {"any_of": ["40 MVA", "40MVA", "40"]} | I153: retrieval | J153: existing
A154: ext-002 | B154: extraction | C154: grounded_qa | D154: exact_match | E154: 100 | F154: Answer using only the passage provided. Reply with the answer alone, no explanation. | G154: Passage: Flight KL872 departs Bengaluru at 02:15 and lands in Amsterdam at 08:40 local time. The aircraft is a Boeing 787-9 configured with 294 seats. Question: How many seats does the aircraft have? | H154: {"answer": "294"} | I154: retrieval | J154: existing
A155: ext-003 | B155: extraction | C155: unanswerable | D155: exact_match | E155: 100 | F155: Answer using only the passage provided. If the passage does not contain the answer, reply with exactly: NOT IN PASSAGE | G155: Passage: The library holds 42,000 volumes and opened in 1974. Membership is free for residents of the district. Question: Who was the architect of the library building? | H155: {"answer": "NOT IN PASSAGE"} | I155: hallucination_resistance | J155: existing
A156: ext-004 | B156: extraction | C156: unanswerable | D156: exact_match | E156: 100 | F156: Answer using only the passage provided. If the passage does not contain the answer, reply with exactly: NOT IN PASSAGE | G156: Passage: Version 3.2 of the parser fixed a memory leak in the tokeniser and reduced startup time by 18 percent. It shipped on a Tuesday. Question: What is the licence of the parser? | H156: {"answer": "NOT IN PASSAGE"} | I156: hallucination_resistance | J156: existing
A157: ext-005 | B157: extraction | C157: grounded_qa | D157: exact_match | E157: 100 | F157: Answer using only the passage provided. Reply with the answer alone, no explanation. | G157: Passage: Three vendors submitted bids. Aurora quoted 1,240,000 with a 14-week delivery. Baseline quoted 1,180,000 with a 22-week delivery. Corvus quoted 1,310,000 with an 11-week delivery. Question: Which vendor quoted the lowest price? | H157: {"answer": "Baseline"} | I157: comparison | J157: existing
A158: ext-006 | B158: extraction | C158: grounded_qa | D158: exact_match | E158: 100 | F158: Answer using only the passage provided. Reply with the answer alone, no explanation. | G158: Passage: Three vendors submitted bids. Aurora quoted 1,240,000 with a 14-week delivery. Baseline quoted 1,180,000 with a 22-week delivery. Corvus quoted 1,310,000 with an 11-week delivery. Question: Which vendor offered the fastest delivery? | H158: {"answer": "Corvus"} | I158: comparison | J158: existing
A159: ext-007 | B159: extraction | C159: grounded_qa | D159: exact_match | E159: 150 | F159: Answer using only the passage provided. Reply with the answer alone, no explanation. | G159: Passage: The incident began at 14:07 when the primary node stopped responding. Failover completed at 14:11. Full service was restored at 14:26 after the cache was rebuilt. Question: How many minutes elapsed between the start of the incident and full restoration? | H159: {"answer": "19"} | I159: computation_from_text | J159: existing
A160: ext-008 | B160: extraction | C160: grounded_qa | D160: exact_match | E160: 150 | F160: Answer using only the passage provided. Reply with the answer alone, no explanation. | G160: Passage: Under the revised policy, employees may carry forward up to 12 unused leave days into the next calendar year. Any days beyond that limit lapse on 31 December. The previous limit was 8 days. Question: By how many days did the carry-forward limit increase? | H160: {"answer": "4"} | I160: computation_from_text | J160: existing
A161: ext-009 | B161: extraction | C161: contradiction | D161: exact_match | E161: 150 | F161: Answer using only the passage provided. Reply with the answer alone, no explanation. | G161: Passage: The report states the survey covered 1,500 households. A footnote on the same page states that 1,500 households were approached but only 1,340 completed the survey. Question: How many households completed the survey? | H161: {"answer": "1340"} | I161: precision, distractor | J161: existing
A162: ext-010 | B162: extraction | C162: grounded_qa | D162: exact_match | E162: 200 | F162: Answer using only the passage provided. Reply with the answer alone, no explanation. | G162: Passage: Sensor A reported 21.4 degrees, sensor B reported 22.9 degrees and sensor C failed to report. The control system uses the mean of all reporting sensors. Question: What value does the control system use? Give one decimal place. | H162: {"any_of": ["22.15", "22.2"]} | I162: computation_from_text | J162: existing
...

Sheet Non-Chinese
A1: Non-Chinese LLMs
A2: Labs headquartered outside China. 'Open' = weights downloadable (licence varies); 'Closed' = API access only.
A4: Model | B4: Lab | C4: Country | D4: Weights | E4: License / Notes | F4: Context (tokens) | G4: Input $/M | H4: Output $/M | I4: API ID / Where | J4: Source
A5: Gemma-SEA-LION v3 9B IT | B5: AI Singapore | C5: Singapore | D5: Open | E5: Gemma Terms - Southeast Asian languages | F5: 8192 | I5: hf: aisingapore/Gemma-SEA-LION-v3-9B-IT | J5: Manual - not on OpenRouter
A6: AI21: Jamba Large 1.7 | B6: AI21 Labs | C6: Israel | D6: Open | E6: Jamba Open Model License | F6: 256000 | G6: 2 | H6: 8 | I6: ai21/jamba-large-1.7 | J6: OpenRouter catalogue
A7: AionLabs: Aion-2.0 | B7: Aion Labs | C7: Israel | D7: Closed | F7: 131072 | G7: 0.8 | H7: 1.6 | I7: aion-labs/aion-2.0 | J7: OpenRouter catalogue
A8: AionLabs: Aion-3.0 | B8: Aion Labs | C8: Israel | D8: Closed | F8: 131072 | G8: 3 | H8: 6 | I8: aion-labs/aion-3.0 | J8: OpenRouter catalogue
A9: AionLabs: Aion-3.0-Mini | B9: Aion Labs | C9: Israel | D9: Closed | F9: 131072 | G9: 0.7 | H9: 1.4 | I9: aion-labs/aion-3.0-mini | J9: OpenRouter catalogue
A10: AionLabs: Aion-RP 1.0 (8B) | B10: Aion Labs | C10: Israel | D10: Open | E10: Llama 3.1 fine-tune | F10: 32768 | G10: 0.8 | H10: 1.6 | I10: aion-labs/aion-rp-llama-3.1-8b | J10: OpenRouter catalogue
A11: AllenAI: Olmo 3 32B Think | B11: Allen Institute for AI | C11: United States | D11: Open | E11: Apache 2.0 (fully open: data + recipes) | F11: 65536 | G11: 0.15 | H11: 0.5 | I11: allenai/olmo-3-32b-think | J11: OpenRouter catalogue
A12: OLMo 2 32B Instruct | B12: Allen Institute for AI | C12: United States | D12: Open | E12: Apache 2.0 (fully open: data + recipes) | F12: 4096 | I12: hf: allenai/OLMo-2-0325-32B-Instruct | J12: Manual - not on OpenRouter
A13: Amazon: Nova 2 Lite | B13: Amazon | C13: United States | D13: Closed | F13: 1000000 | G13: 0.3 | H13: 2.5 | I13: amazon/nova-2-lite-v1 | J13: OpenRouter catalogue
A14: Amazon: Nova Lite 1.0 | B14: Amazon | C14: United States | D14: Closed | F14: 300000 | G14: 0.06 | H14: 0.24 | I14: amazon/nova-lite-v1 | J14: OpenRouter catalogue
A15: Amazon: Nova Micro 1.0 | B15: Amazon | C15: United States | D15: Closed | F15: 128000 | G15: 0.035 | H15: 0.14 | I15: amazon/nova-micro-v1 | J15: OpenRouter catalogue
A16: Amazon: Nova Premier 1.0 | B16: Amazon | C16: United States | D16: Closed | F16: 1000000 | G16: 2.5 | H16: 12.5 | I16: amazon/nova-premier-v1 | J16: OpenRouter catalogue
A17: Amazon: Nova Pro 1.0 | B17: Amazon | C17: United States | D17: Closed | F17: 300000 | G17: 0.8 | H17: 3.2 | I17: amazon/nova-pro-v1 | J17: OpenRouter catalogue
A18: Magnum v4 72B | B18: Anthracite (community) | C18: Community | D18: Open | E18: Open weights / community fine-tune | F18: 16384 | G18: 3 | H18: 5 | I18: anthracite-org/magnum-v4-72b | J18: OpenRouter catalogue
A19: Anthropic: Claude 3 Haiku | B19: Anthropic | C19: United States | D19: Closed | F19: 200000 | G19: 0.25 | H19: 1.25 | I19: anthropic/claude-3-haiku | J19: OpenRouter catalogue
A20: Anthropic: Claude Fable 5 | B20: Anthropic | C20: United States | D20: Closed | F20: 1000000 | G20: 10 | H20: 50 | I20: anthropic/claude-fable-5 | J20: OpenRouter catalogue
A21: Anthropic: Claude Haiku 4.5 | B21: Anthropic | C21: United States | D21: Closed | F21: 200000 | G21: 1 | H21: 5 | I21: anthropic/claude-haiku-4.5 | J21: OpenRouter catalogue
A22: Anthropic: Claude Opus 4 | B22: Anthropic | C22: United States | D22: Closed | F22: 200000 | G22: 15 | H22: 75 | I22: anthropic/claude-opus-4 | J22: OpenRouter catalogue
A23: Anthropic: Claude Opus 4.1 | B23: Anthropic | C23: United States | D23: Closed | F23: 200000 | G23: 15 | H23: 75 | I23: anthropic/claude-opus-4.1 | J23: OpenRouter catalogue
A24: Anthropic: Claude Opus 4.5 | B24: Anthropic | C24: United States | D24: Closed | F24: 200000 | G24: 5 | H24: 25 | I24: anthropic/claude-opus-4.5 | J24: OpenRouter catalogue
A25: Anthropic: Claude Opus 4.6 | B25: Anthropic | C25: United States | D25: Closed | F25: 1000000 | G25: 5 | H25: 25 | I25: anthropic/claude-opus-4.6 | J25: OpenRouter catalogue
A26: Anthropic: Claude Opus 4.7 | B26: Anthropic | C26: United States | D26: Closed | F26: 1000000 | G26: 5 | H26: 25 | I26: anthropic/claude-opus-4.7 | J26: OpenRouter catalogue
A27: Anthropic: Claude Opus 4.7 (Fast) | B27: Anthropic | C27: United States | D27: Closed | F27: 1000000 | G27: 30 | H27: 150 | I27: anthropic/claude-opus-4.7-fast | J27: OpenRouter catalogue
A28: Anthropic: Claude Opus 4.8 | B28: Anthropic | C28: United States | D28: Closed | F28: 1000000 | G28: 5 | H28: 25 | I28: anthropic/claude-opus-4.8 | J28: OpenRouter catalogue
A29: Anthropic: Claude Opus 4.8 (Fast) | B29: Anthropic | C29: United States | D29: Closed | F29: 1000000 | G29: 10 | H29: 50 | I29: anthropic/claude-opus-4.8-fast | J29: OpenRouter catalogue
A30: Anthropic: Claude Sonnet 4 | B30: Anthropic | C30: United States | D30: Closed | F30: 1000000 | G30: 3 | H30: 15 | I30: anthropic/claude-sonnet-4 | J30: OpenRouter catalogue
... A33: Anthropic: Claude Sonnet 5 | B33: Anthropic | C33: United States | D33: Closed | F33: 1000000 | G33: 2 | H33: 10 | I33: anthropic/claude-sonnet-5 | J33: OpenRouter catalogue
A34: Claude Mythos 5 | B34: Anthropic | C34: United States | D34: Closed | E34: Gated to approved organisations; not publicly routable | I34: Anthropic API (restricted) | J34: Manual - not on OpenRouter
A35: Claude Opus 5 | B35: Anthropic | C35: United States | D35: Closed | F35: 1000000 | G35: 5 | H35: 25 | I35: anthropic/claude-opus-5 | J35: OpenRouter catalogue
A36: Claude Opus 5 (Fast) | B36: Anthropic | C36: United States | D36: Closed | F36: 1000000 | G36: 10 | H36: 50 | I36: anthropic/claude-opus-5-fast | J36: OpenRouter catalogue
A37: Arcee AI: Trinity Large Thinking | B37: Arcee AI | C37: United States | D37: Open | E37: Open weights / community fine-tune | F37: 262144 | G37: 0.22 | H37: 0.85 | I37: arcee-ai/trinity-large-thinking | J37: OpenRouter catalogue
A38: Arcee AI: Virtuoso Large | B38: Arcee AI | C38: United States | D38: Open | E38: Open weights / community fine-tune | F38: 131072 | G38: 0.75 | H38: 1.2 | I38: arcee-ai/virtuoso-large | J38: OpenRouter catalogue
A39: Venice: Uncensored | B39: Cognitive Computations | C39: United States | D39: Open | E39: Open weights / community fine-tune | F39: 128000 | G39: 0.2 | H39: 0.9 | I39: cognitivecomputations/dolphin-mistral-24b-venice-edition | J39: OpenRouter catalogue
A40: Aya Expanse 32B | B40: Cohere | C40: Canada | D40: Open | E40: CC-BY-NC 4.0 - 23 languages | F40: 128000 | I40: cohere: c4ai-aya-expanse-32b | J40: Manual - not on OpenRouter
A41: Cohere: Command A | B41: Cohere | C41: Canada | D41: Open | E41: CC-BY-NC 4.0 (non-commercial) | F41: 256000 | G41: 2.5 | H41: 10 | I41: cohere/command-a | J41: OpenRouter catalogue
A42: Cohere: Command R (08-2024) | B42: Cohere | C42: Canada | D42: Open | E42: CC-BY-NC 4.0 (non-commercial) | F42: 128000 | G42: 0.15 | H42: 0.6 | I42: cohere/command-r-08-2024 | J42: OpenRouter catalogue
A43: Cohere: Command R+ (08-2024) | B43: Cohere | C43: Canada | D43: Open | E43: CC-BY-NC 4.0 (non-commercial) | F43: 128000 | G43: 2.5 | H43: 10 | I43: cohere/command-r-plus-08-2024 | J43: OpenRouter catalogue
A44: Cohere: Command R7B (12-2024) | B44: Cohere | C44: Canada | D44: Open | E44: CC-BY-NC 4.0 (non-commercial) | F44: 128000 | G44: 0.0375 | H44: 0.15 | I44: cohere/command-r7b-12-2024 | J44: OpenRouter catalogue
A45: Deep Cogito: Cogito v2.1 671B | B45: Deep Cogito | C45: United States | D45: Open | E45: Open weights / community fine-tune | F45: 128000 | G45: 1.25 | H45: 1.25 | I45: deepcogito/cogito-v2.1-671b | J45: OpenRouter catalogue
A46: Google: Gemini 2.5 Flash | B46: Google DeepMind | C46: United States | D46: Closed | F46: 1048576 | G46: 0.3 | H46: 2.5 | I46: google/gemini-2.5-flash | J46: OpenRouter catalogue
A47: Google: Gemini 2.5 Flash Lite | B47: Google DeepMind | C47: United States | D47: Closed | F47: 1048576 | G47: 0.1 | H47: 0.4 | I47: google/gemini-2.5-flash-lite | J47: OpenRouter catalogue
A48: Google: Gemini 2.5 Pro | B48: Google DeepMind | C48: United States | D48: Closed | F48: 1048576 | G48: 1.25 | H48: 10 | I48: google/gemini-2.5-pro | J48: OpenRouter catalogue
A49: Google: Gemini 2.5 Pro Preview 05-06 | B49: Google DeepMind | C49: United States | D49: Closed | F49: 1048576 | G49: 1.25 | H49: 10 | I49: google/gemini-2.5-pro-preview-05-06 | J49: OpenRouter catalogue
A50: Google: Gemini 2.5 Pro Preview 06-05 | B50: Google DeepMind | C50: United States | D50: Closed | F50: 1048576 | G50: 1.25 | H50: 10 | I50: google/gemini-2.5-pro-preview | J50: OpenRouter catalogue
A51: Google: Gemini 3 Flash Preview | B51: Google DeepMind | C51: United States | D51: Closed | F51: 1048576 | G51: 0.5 | H51: 3 | I51: google/gemini-3-flash-preview | J51: OpenRouter catalogue
A52: Google: Gemini 3.1 Flash Lite | B52: Google DeepMind | C52: United States | D52: Closed | F52: 1048576 | G52: 0.25 | H52: 1.5 | I52: google/gemini-3.1-flash-lite | J52: OpenRouter catalogue
A53: Google: Gemini 3.1 Flash Lite Preview | B53: Google DeepMind | C53: United States | D53: Closed | F53: 1048576 | G53: 0.25 | H53: 1.5 | I53: google/gemini-3.1-flash-lite-preview | J53: OpenRouter catalogue
A54: Google: Gemini 3.1 Pro Preview | B54: Google DeepMind | C54: United States | D54: Closed | F54: 1048576 | G54: 2 | H54: 12 | I54: google/gemini-3.1-pro-preview | J54: OpenRouter catalogue
A55: Google: Gemini 3.1 Pro Preview Custom Tools | B55: Google DeepMind | C55: United States | D55: Closed | F55: 1048576 | G55: 2 | H55: 12 | I55: google/gemini-3.1-pro-preview-customtools | J55: OpenRouter catalogue
A56: Google: Gemini 3.5 Flash | B56: Google DeepMind | C56: United States | D56: Closed | F56: 1048576 | G56: 1.5 | H56: 9 | I56: google/gemini-3.5-flash | J56: OpenRouter catalogue
A57: Google: Gemini 3.5 Flash Lite | B57: Google DeepMind | C57: United States | D57: Closed | F57: 1048576 | G57: 0.3 | H57: 2.5 | I57: google/gemini-3.5-flash-lite | J57: OpenRouter catalogue
A58: Google: Gemini 3.6 Flash | B58: Google DeepMind | C58: United States | D58: Closed | F58: 1048576 | G58: 1.5 | H58: 7.5 | I58: google/gemini-3.6-flash | J58: OpenRouter catalogue
A59: Google: Lyria 3 Clip Preview | B59: Google DeepMind | C59: United States | D59: Closed | F59: 1048576 | I59: google/lyria-3-clip-preview | J59: OpenRouter catalogue
A60: Google: Lyria 3 Pro Preview | B60: Google DeepMind | C60: United States | D60: Closed | F60: 1048576 | I60: google/lyria-3-pro-preview | J60: OpenRouter catalogue
A61: Google: Nano Banana (Gemini 2.5 Flash Image) | B61: Google DeepMind | C61: United States | D61: Closed | F61: 32768 | G61: 0.3 | H61: 2.5 | I61: google/gemini-2.5-flash-image | J61: OpenRouter catalogue
A62: Google: Nano Banana 2 (Gemini 3.1 Flash Image Preview) | B62: Google DeepMind | C62: United States | D62: Closed | F62: 65536 | G62: 0.5 | H62: 3 | I62: google/gemini-3.1-flash-image-preview | J62: OpenRouter catalogue
A63: Google: Nano Banana 2 (Gemini 3.1 Flash Image) | B63: Google DeepMind | C63: United States | D63: Closed | F63: 131072 | G63: 0.5 | H63: 3 | I63: google/gemini-3.1-flash-image | J63: OpenRouter catalogue
A64: Google: Nano Banana 2 Lite (Gemini 3.1 Flash Lite Image) | B64: Google DeepMind | C64: United States | D64: Closed | F64: 65536 | G64: 0.25 | H64: 1.5 | I64: google/gemini-3.1-flash-lite-image | J64: OpenRouter catalogue
A65: Google: Nano Banana Pro (Gemini 3 Pro Image Preview) | B65: Google DeepMind | C65: United States | D65: Closed | F65: 65536 | G65: 2 | H65: 12 | I65: google/gemini-3-pro-image-preview | J65: OpenRouter catalogue
A66: Google: Nano Banana Pro (Gemini 3 Pro Image) | B66: Google DeepMind | C66: United States | D66: Closed | F66: 131072 | G66: 2 | H66: 12 | I66: google/gemini-3-pro-image | J66: OpenRouter catalogue
A67: Google: Gemma 2 27B | B67: Google DeepMind | C67: United States | D67: Open | E67: Gemma Terms of Use | F67: 8192 | G67: 0.65 | H67: 0.65 | I67: google/gemma-2-27b-it | J67: OpenRouter catalogue
A68: Google: Gemma 3 12B | B68: Google DeepMind | C68: United States | D68: Open | E68: Gemma Terms of Use | F68: 131072 | G68: 0.05 | H68: 0.15 | I68: google/gemma-3-12b-it | J68: OpenRouter catalogue
A69: Google: Gemma 3 27B | B69: Google DeepMind | C69: United States | D69: Open | E69: Gemma Terms of Use | F69: 262144 | G69: 0.08 | H69: 0.45 | I69: google/gemma-3-27b-it | J69: OpenRouter catalogue
A70: Google: Gemma 3 4B | B70: Google DeepMind | C70: United States | D70: Open | E70: Gemma Terms of Use | F70: 131072 | G70: 0.05 | H70: 0.1 | I70: google/gemma-3-4b-it | J70: OpenRouter catalogue
A71: Google: Gemma 3n 4B | B71: Google DeepMind | C71: United States | D71: Open | E71: Gemma Terms of Use | F71: 32768 | G71: 0.06 | H71: 0.12 | I71: google/gemma-3n-e4b-it | J71: OpenRouter catalogue
A72: Google: Gemma 4 26B A4B | B72: Google DeepMind | C72: United States | D72: Open | E72: Gemma Terms of Use | F72: 262144 | G72: 0.07 | H72: 0.34 | I72: google/gemma-4-26b-a4b-it | J72: OpenRouter catalogue
A73: Google: Gemma 4 31B | B73: Google DeepMind | C73: United States | D73: Open | E73: Gemma Terms of Use | F73: 262144 | G73: 0.1 | H73: 0.34 | I73: google/gemma-4-31b-it | J73: OpenRouter catalogue
A74: MythoMax 13B | B74: Gryphe (community) | C74: Community | D74: Open | E74: Open weights / community fine-tune | F74: 8192 | G74: 0.06 | H74: 0.06 | I74: gryphe/mythomax-l2-13b | J74: OpenRouter catalogue
A75: IBM: Granite 4.0 Micro | B75: IBM | C75: United States | D75: Open | E75: Apache 2.0 | F75: 131000 | G75: 0.017 | H75: 0.112 | I75: ibm-granite/granite-4.0-h-micro | J75: OpenRouter catalogue
A76: IBM: Granite 4.1 8B | B76: IBM | C76: United States | D76: Open | E76: Apache 2.0 | F76: 131072 | G76: 0.05 | H76: 0.1 | I76: ibm-granite/granite-4.1-8b | J76: OpenRouter catalogue
A77: Inception: Mercury 2 | B77: Inception Labs | C77: United States | D77: Closed | F77: 128000 | G77: 0.25 | H77: 0.75 | I77: inception/mercury-2 | J77: OpenRouter catalogue
A78: EXAONE 4.0 32B | B78: LG AI Research | C78: South Korea | D78: Open | E78: EXAONE AI Model License (non-commercial) | F78: 131072 | I78: hf: LGAI-EXAONE/EXAONE-4.0-32B | J78: Manual - not on OpenRouter
A79: Mancer: Weaver (alpha) | B79: Mancer | C79: Community | D79: Closed | F79: 8000 | G79: 0.5 | H79: 0.75 | I79: mancer/weaver | J79: OpenRouter catalogue
A80: Meta: Muse Spark 1.1 | B80: Meta | C80: United States | D80: Closed | E80: UNVERIFIED - new Meta hosted model | F80: 1048576 | G80: 1.25 | H80: 4.25 | I80: meta/muse-spark-1.1 | J80: OpenRouter catalogue
A81: Meta: Llama 3.1 70B Instruct | B81: Meta | C81: United States | D81: Open | E81: Llama Community License | F81: 131072 | G81: 0.4 | H81: 0.4 | I81: meta-llama/llama-3.1-70b-instruct | J81: OpenRouter catalogue
A82: Meta: Llama 3.1 8B Instruct | B82: Meta | C82: United States | D82: Open | E82: Llama Community License | F82: 131072 | G82: 0.05 | H82: 0.08 | I82: meta-llama/llama-3.1-8b-instruct | J82: OpenRouter catalogue
A83: Meta: Llama 3.2 1B Instruct | B83: Meta | C83: United States | D83: Open | E83: Llama Community License | F83: 60000 | G83: 0.027 | H83: 0.201 | I83: meta-llama/llama-3.2-1b-instruct | J83: OpenRouter catalogue
A84: Meta: Llama 3.2 3B Instruct | B84: Meta | C84: United States | D84: Open | E84: Llama Community License | F84: 131072 | G84: 0.05 | H84: 0.33 | I84: meta-llama/llama-3.2-3b-instruct | J84: OpenRouter catalogue
A85: Meta: Llama 3.3 70B Instruct | B85: Meta | C85: United States | D85: Open | E85: Llama Community License | F85: 131072 | G85: 0.13 | H85: 0.4 | I85: meta-llama/llama-3.3-70b-instruct | J85: OpenRouter catalogue
A86: Meta: Llama 4 Maverick | B86: Meta | C86: United States | D86: Open | E86: Llama Community License | F86: 1048576 | G86: 0.2 | H86: 0.8 | I86: meta-llama/llama-4-maverick | J86: OpenRouter catalogue
A87: Meta: Llama 4 Scout | B87: Meta | C87: United States | D87: Open | E87: Llama Community License | F87: 1310720 | G87: 0.1 | H87: 0.3 | I87: meta-llama/llama-4-scout | J87: OpenRouter catalogue
A88: Meta: Llama Guard 4 12B | B88: Meta | C88: United States | D88: Open | E88: Llama Community License | F88: 1048576 | G88: 0.18 | H88: 0.18 | I88: meta-llama/llama-guard-4-12b | J88: OpenRouter catalogue
A89: Microsoft: Phi 4 | B89: Microsoft | C89: United States | D89: Open | E89: MIT | F89: 16384 | G89: 0.07 | H89: 0.14 | I89: microsoft/phi-4 | J89: OpenRouter catalogue
A90: WizardLM-2 8x22B | B90: Microsoft | C90: United States | D90: Open | E90: MIT | F90: 65535 | G90: 0.62 | H90: 0.62 | I90: microsoft/wizardlm-2-8x22b | J90: OpenRouter catalogue
A91: Mistral Large | B91: Mistral AI | C91: France | D91: Closed | E91: Commercial API tier | F91: 128000 | G91: 2 | H91: 6 | I91: mistralai/mistral-large | J91: OpenRouter catalogue
... A109: Mistral: Voxtral Small 24B 2507 | B109: Mistral AI | C109: France | D109: Open | E109: Apache 2.0 (Small/Ministral/Mixtral/Nemo line) | F109: 32000 | G109: 0.1 | H109: 0.3 | I109: mistralai/voxtral-small-24b-2507 | J109: OpenRouter catalogue
A110: Morph: Morph V3 Fast | B110: Morph | C110: United States | D110: Closed | F110: 81920 | G110: 0.8 | H110: 1.2 | I110: morph/morph-v3-fast | J110: OpenRouter catalogue
A111: Morph: Morph V3 Large | B111: Morph | C111: United States | D111: Closed | F111: 262144 | G111: 0.9 | H111: 1.9 | I111: morph/morph-v3-large | J111: OpenRouter catalogue
A112: Nous: Hermes 3 405B Instruct | B112: Nous Research | C112: United States | D112: Open | E112: Open weights / community fine-tune | F112: 131072 | G112: 1 | H112: 1 | I112: nousresearch/hermes-3-llama-3.1-405b | J112: OpenRouter catalogue
A113: Nous: Hermes 3 70B Instruct | B113: Nous Research | C113: United States | D113: Open | E113: Open weights / community fine-tune | F113: 131072 | G113: 0.7 | H113: 0.7 | I113: nousresearch/hermes-3-llama-3.1-70b | J113: OpenRouter catalogue
A114: Nous: Hermes 4 405B | B114: Nous Research | C114: United States | D114: Open | E114: Open weights / community fine-tune | F114: 131072 | G114: 1 | H114: 3 | I114: nousresearch/hermes-4-405b | J114: OpenRouter catalogue
A115: Nous: Hermes 4 70B | B115: Nous Research | C115: United States | D115: Open | E115: Open weights / community fine-tune | F115: 131072 | G115: 0.13 | H115: 0.4 | I115: nousresearch/hermes-4-70b | J115: OpenRouter catalogue
A116: NVIDIA: Nemotron 3 Nano 30B A3B | B116: NVIDIA | C116: United States | D116: Open | E116: NVIDIA Open Model License | F116: 262144 | G116: 0.05 | H116: 0.2 | I116: nvidia/nemotron-3-nano-30b-a3b | J116: OpenRouter catalogue
A117: NVIDIA: Nemotron 3 Super | B117: NVIDIA | C117: United States | D117: Open | E117: NVIDIA Open Model License | F117: 1000000 | G117: 0.085 | H117: 0.4 | I117: nvidia/nemotron-3-super-120b-a12b | J117: OpenRouter catalogue
A118: NVIDIA: Nemotron 3 Ultra | B118: NVIDIA | C118: United States | D118: Open | E118: NVIDIA Open Model License | F118: 512288 | G118: 0.6 | H118: 3.6 | I118: nvidia/nemotron-3-ultra-550b-a55b | J118: OpenRouter catalogue
A119: OpenAI: GPT Audio | B119: OpenAI | C119: United States | D119: Closed | F119: 128000 | G119: 2.5 | H119: 10 | I119: openai/gpt-audio | J119: OpenRouter catalogue
A120: OpenAI: GPT Audio Mini | B120: OpenAI | C120: United States | D120: Closed | F120: 128000 | G120: 0.6 | H120: 2.4 | I120: openai/gpt-audio-mini | J120: OpenRouter catalogue
...

Sheet Chinese
A1: Chinese LLMs
A2: Labs headquartered in mainland China. Many of these run on Western infrastructure (Groq, Together, Fireworks, NVIDIA NIM) - hosting does not change the classification.
A4: Model | B4: Lab | C4: Country | D4: Weights | E4: License / Notes | F4: Context (tokens) | G4: Input $/M | H4: Output $/M | I4: API ID / Where | J4: Source
A5: Qwen: Qwen Plus 0728 | B5: Alibaba (Qwen) | C5: China | D5: Closed | E5: Hosted tier (Alibaba Cloud / Model Studio) | F5: 1000000 | G5: 0.26 | H5: 0.78 | I5: qwen/qwen-plus-2025-07-28 | J5: OpenRouter catalogue
A6: Qwen: Qwen Plus 0728 (thinking) | B6: Alibaba (Qwen) | C6: China | D6: Closed | E6: Hosted tier (Alibaba Cloud / Model Studio) | F6: 1000000 | G6: 0.4 | H6: 1.2 | I6: qwen/qwen-plus-2025-07-28:thinking | J6: OpenRouter catalogue
A7: Qwen: Qwen-Plus | B7: Alibaba (Qwen) | C7: China | D7: Closed | E7: Hosted tier (Alibaba Cloud / Model Studio) | F7: 1000000 | G7: 0.26 | H7: 0.78 | I7: qwen/qwen-plus | J7: OpenRouter catalogue
A8: Qwen: Qwen3 Max | B8: Alibaba (Qwen) | C8: China | D8: Closed | E8: Hosted tier (Alibaba Cloud / Model Studio) | F8: 262144 | G8: 0.78 | H8: 3.9 | I8: qwen/qwen3-max | J8: OpenRouter catalogue
A9: Qwen: Qwen3 Max Thinking | B9: Alibaba (Qwen) | C9: China | D9: Closed | E9: Hosted tier (Alibaba Cloud / Model Studio) | F9: 262144 | G9: 0.78 | H9: 3.9 | I9: qwen/qwen3-max-thinking | J9: OpenRouter catalogue
A10: Qwen: Qwen3.5 Plus 2026-02-15 | B10: Alibaba (Qwen) | C10: China | D10: Closed | E10: Hosted tier (Alibaba Cloud / Model Studio) | F10: 1000000 | G10: 0.26 | H10: 1.56 | I10: qwen/qwen3.5-plus-02-15 | J10: OpenRouter catalogue
A11: Qwen: Qwen3.5 Plus 2026-04-20 | B11: Alibaba (Qwen) | C11: China | D11: Closed | E11: Hosted tier (Alibaba Cloud / Model Studio) | F11: 1000000 | G11: 0.3 | H11: 1.8 | I11: qwen/qwen3.5-plus-20260420 | J11: OpenRouter catalogue
A12: Qwen: Qwen3.5-Flash | B12: Alibaba (Qwen) | C12: China | D12: Closed | E12: Hosted tier (Alibaba Cloud / Model Studio) | F12: 1000000 | G12: 0.065 | H12: 0.26 | I12: qwen/qwen3.5-flash-02-23 | J12: OpenRouter catalogue
A13: Qwen: Qwen3.6 Flash | B13: Alibaba (Qwen) | C13: China | D13: Closed | E13: Hosted tier (Alibaba Cloud / Model Studio) | F13: 1000000 | G13: 0.1875 | H13: 1.125 | I13: qwen/qwen3.6-flash | J13: OpenRouter catalogue
A14: Qwen: Qwen3.6 Max Preview | B14: Alibaba (Qwen) | C14: China | D14: Closed | E14: Hosted tier (Alibaba Cloud / Model Studio) | F14: 262144 | G14: 1.027 | H14: 6.162 | I14: qwen/qwen3.6-max-preview | J14: OpenRouter catalogue
A15: Qwen: Qwen3.6 Plus | B15: Alibaba (Qwen) | C15: China | D15: Closed | E15: Hosted tier (Alibaba Cloud / Model Studio) | F15: 1000000 | G15: 0.325 | H15: 1.95 | I15: qwen/qwen3.6-plus | J15: OpenRouter catalogue
A16: Qwen: Qwen3.7 Flash | B16: Alibaba (Qwen) | C16: China | D16: Closed | E16: Hosted tier (Alibaba Cloud / Model Studio) | F16: 1000000 | G16: 0.03 | H16: 0.13 | I16: qwen/qwen3.7-flash | J16: OpenRouter catalogue
... A55: inclusionAI: Ring-2.6-1T | B55: Ant Group (InclusionAI) | C55: China | D55: Open | E55: Apache 2.0 (Ling / Ring) | F55: 262144 | G55: 0.075 | H55: 0.625 | I55: inclusionai/ring-2.6-1t | J55: OpenRouter catalogue
A56: ERNIE 5.x (hosted tiers) | B56: Baidu | C56: China | D56: Closed | E56: UNVERIFIED version - Qianfan platform only | I56: Baidu Qianfan | J56: Manual - not on OpenRouter
A57: Baidu: ERNIE 4.5 VL 424B A47B | B57: Baidu | C57: China | D57: Open | E57: Apache 2.0 (ERNIE 4.5) | F57: 123000 | G57: 0.42 | H57: 1.25 | I57: baidu/ernie-4.5-vl-424b-a47b | J57: OpenRouter catalogue
A58: Doubao (hosted tiers) | B58: ByteDance | C58: China | D58: Closed | E58: UNVERIFIED version - Volcano Ark only | I58: Volcano Ark | J58: Manual - not on OpenRouter
A59: ByteDance: UI-TARS 7B | B59: ByteDance | C59: China | D59: Open | E59: Apache 2.0 (UI-TARS) | F59: 128000 | G59: 0.1 | H59: 0.2 | I59: bytedance/ui-tars-1.5-7b | J59: OpenRouter catalogue
A60: ByteDance Seed: Seed 1.6 | B60: ByteDance Seed | C60: China | D60: Closed | E60: Volcano Ark hosted tier | F60: 262144 | G60: 0.25 | H60: 2 | I60: bytedance-seed/seed-1.6 | J60: OpenRouter catalogue
A61: ByteDance Seed: Seed 1.6 Flash | B61: ByteDance Seed | C61: China | D61: Closed | E61: Volcano Ark hosted tier | F61: 262144 | G61: 0.075 | H61: 0.3 | I61: bytedance-seed/seed-1.6-flash | J61: OpenRouter catalogue
A62: ByteDance Seed: Seed-2.0-Lite | B62: ByteDance Seed | C62: China | D62: Closed | E62: Volcano Ark hosted tier | F62: 262144 | G62: 0.25 | H62: 2 | I62: bytedance-seed/seed-2.0-lite | J62: OpenRouter catalogue
A63: ByteDance Seed: Seed-2.0-Mini | B63: ByteDance Seed | C63: China | D63: Closed | E63: Volcano Ark hosted tier | F63: 262144 | G63: 0.1 | H63: 0.4 | I63: bytedance-seed/seed-2.0-mini | J63: OpenRouter catalogue
A64: DeepSeek: DeepSeek V3 | B64: DeepSeek | C64: China | D64: Open | E64: MIT | F64: 163840 | G64: 0.2574 | H64: 1.0287 | I64: deepseek/deepseek-chat | J64: OpenRouter catalogue
A65: DeepSeek: DeepSeek V3 0324 | B65: DeepSeek | C65: China | D65: Open | E65: MIT | F65: 163840 | G65: 0.27 | H65: 1.12 | I65: deepseek/deepseek-chat-v3-0324 | J65: OpenRouter catalogue
A66: DeepSeek: DeepSeek V3.1 | B66: DeepSeek | C66: China | D66: Open | E66: MIT | F66: 163840 | G66: 0.25 | H66: 0.95 | I66: deepseek/deepseek-chat-v3.1 | J66: OpenRouter catalogue
A67: DeepSeek: DeepSeek V3.1 Terminus | B67: DeepSeek | C67: China | D67: Open | E67: MIT | F67: 163840 | G67: 0.27 | H67: 1 | I67: deepseek/deepseek-v3.1-terminus | J67: OpenRouter catalogue
A68: DeepSeek: DeepSeek V3.2 | B68: DeepSeek | C68: China | D68: Open | E68: MIT | F68: 163840 | G68: 0.269 | H68: 0.4 | I68: deepseek/deepseek-v3.2 | J68: OpenRouter catalogue
A69: DeepSeek: DeepSeek V3.2 Exp | B69: DeepSeek | C69: China | D69: Open | E69: MIT | F69: 163840 | G69: 0.27 | H69: 0.41 | I69: deepseek/deepseek-v3.2-exp | J69: OpenRouter catalogue
A70: DeepSeek: DeepSeek V4 Flash | B70: DeepSeek | C70: China | D70: Open | E70: MIT | F70: 1048576 | G70: 0.14 | H70: 0.28 | I70: deepseek/deepseek-v4-flash | J70: OpenRouter catalogue
... A75: DeepSeek: R1 Distill Llama 70B | B75: DeepSeek | C75: China | D75: Open | E75: MIT | F75: 8192 | G75: 0.8 | H75: 0.8 | I75: deepseek/deepseek-r1-distill-llama-70b | J75: OpenRouter catalogue
A76: Spark (Xinghuo) | B76: iFlytek | C76: China | D76: Closed | E76: UNVERIFIED version - domestic API only | I76: iFlytek API | J76: Manual - not on OpenRouter
A77: Kwaipilot: KAT-Coder-Air V2.5 | B77: Kuaishou (Kwaipilot) | C77: China | D77: Open | E77: UNVERIFIED - confirm KAT-Coder weights on Hugging Face | F77: 256000 | G77: 0.15 | H77: 0.6 | I77: kwaipilot/kat-coder-air-v2.5 | J77: OpenRouter catalogue
A78: Kwaipilot: KAT-Coder-Pro V2 | B78: Kuaishou (Kwaipilot) | C78: China | D78: Open | E78: UNVERIFIED - confirm KAT-Coder weights on Hugging Face | F78: 262144 | G78: 0.3 | H78: 1.2 | I78: kwaipilot/kat-coder-pro-v2 | J78: OpenRouter catalogue
A79: Kwaipilot: KAT-Coder-Pro V2.5 | B79: Kuaishou (Kwaipilot) | C79: China | D79: Open | E79: UNVERIFIED - confirm KAT-Coder weights on Hugging Face | F79: 256000 | G79: 0.74 | H79: 2.96 | I79: kwaipilot/kat-coder-pro-v2.5 | J79: OpenRouter catalogue
A80: Meituan: LongCat 2.0 | B80: Meituan | C80: China | D80: Open | E80: UNVERIFIED - confirm weights release for this version | F80: 1048756 | G80: 0.3 | H80: 1.2 | I80: meituan/longcat-2.0 | J80: OpenRouter catalogue
A81: MiniMax: MiniMax M1 | B81: MiniMax | C81: China | D81: Open | E81: Apache 2.0 / MIT | F81: 1000000 | G81: 0.55 | H81: 2.2 | I81: minimax/minimax-m1 | J81: OpenRouter catalogue
A82: MiniMax: MiniMax M2 | B82: MiniMax | C82: China | D82: Open | E82: Apache 2.0 / MIT | F82: 204800 | G82: 0.255 | H82: 1.02 | I82: minimax/minimax-m2 | J82: OpenRouter catalogue
A83: MiniMax: MiniMax M2-her | B83: MiniMax | C83: China | D83: Open | E83: Apache 2.0 / MIT | F83: 65536 | G83: 0.3 | H83: 1.2 | I83: minimax/minimax-m2-her | J83: OpenRouter catalogue
A84: MiniMax: MiniMax M2.1 | B84: MiniMax | C84: China | D84: Open | E84: Apache 2.0 / MIT | F84: 204800 | G84: 0.3 | H84: 1.2 | I84: minimax/minimax-m2.1 | J84: OpenRouter catalogue
A85: MiniMax: MiniMax M2.5 | B85: MiniMax | C85: China | D85: Open | E85: Apache 2.0 / MIT | F85: 204800 | G85: 0.15 | H85: 0.9 | I85: minimax/minimax-m2.5 | J85: OpenRouter catalogue
A86: MiniMax: MiniMax M2.7 | B86: MiniMax | C86: China | D86: Open | E86: Apache 2.0 / MIT | F86: 204800 | G86: 0.25 | H86: 1 | I86: minimax/minimax-m2.7 | J86: OpenRouter catalogue
A87: MiniMax: MiniMax M3 | B87: MiniMax | C87: China | D87: Open | E87: Apache 2.0 / MIT | F87: 1048576 | G87: 0.3 | H87: 1.2 | I87: minimax/minimax-m3 | J87: OpenRouter catalogue
A88: MiniMax: MiniMax-01 | B88: MiniMax | C88: China | D88: Open | E88: Apache 2.0 / MIT | F88: 1000192 | G88: 0.2 | H88: 1.1 | I88: minimax/minimax-01 | J88: OpenRouter catalogue
... A97: Nex AGI: Nex-N2-Pro | B97: Nex AGI | C97: China | D97: Open | E97: UNVERIFIED - confirm weights release for this version | F97: 262144 | G97: 0.25 | H97: 1 | I97: nex-agi/nex-n2-pro | J97: OpenRouter catalogue
A98: SenseChat | B98: SenseTime | C98: China | D98: Closed | E98: UNVERIFIED version - domestic API only | I98: SenseTime API | J98: Manual - not on OpenRouter
A99: InternLM3 8B Instruct | B99: Shanghai AI Laboratory | C99: China | D99: Open | E99: Apache 2.0 | F99: 32768 | I99: hf: internlm/internlm3-8b-instruct | J99: Manual - not on OpenRouter
A100: StepFun: Step 3.5 Flash | B100: StepFun | C100: China | D100: Open | E100: UNVERIFIED - confirm weights release for this version | F100: 262144 | G100: 0.1 | H100: 0.3 | I100: stepfun/step-3.5-flash | J100: OpenRouter catalogue
A101: StepFun: Step 3.7 Flash | B101: StepFun | C101: China | D101: Open | E101: UNVERIFIED - confirm weights release for this version | F101: 262144 | G101: 0.2 | H101: 1.15 | I101: stepfun/step-3.7-flash | J101: OpenRouter catalogue
A102: Tencent: Hy3 | B102: Tencent | C102: China | D102: Closed | E102: UNVERIFIED - HY3 weights release not confirmed | F102: 262144 | G102: 0.132 | H102: 0.528 | I102: tencent/hy3 | J102: OpenRouter catalogue
A103: Tencent: Hy3 preview | B103: Tencent | C103: China | D103: Closed | E103: UNVERIFIED - HY3 weights release not confirmed | F103: 262144 | G103: 0.063 | H103: 0.21 | I103: tencent/hy3-preview | J103: OpenRouter catalogue
A104: Tencent: Hunyuan A13B Instruct | B104: Tencent | C104: China | D104: Open | E104: Tencent Hunyuan Community License | F104: 131072 | G104: 0.14 | H104: 0.57 | I104: tencent/hunyuan-a13b-instruct | J104: OpenRouter catalogue
A105: Xiaomi: MiMo-V2.5 | B105: Xiaomi | C105: China | D105: Open | E105: UNVERIFIED - confirm weights release for this version | F105: 1050000 | G105: 0.14 | H105: 0.28 | I105: xiaomi/mimo-v2.5 | J105: OpenRouter catalogue
A106: Xiaomi: MiMo-V2.5-Pro | B106: Xiaomi | C106: China | D106: Open | E106: UNVERIFIED - confirm weights release for this version | F106: 1050000 | G106: 0.435 | H106: 0.87 | I106: xiaomi/mimo-v2.5-pro | J106: OpenRouter catalogue
A107: Z.ai: GLM 4.5 | B107: Zhipu AI / Z.ai | C107: China | D107: Open | E107: MIT | F107: 131072 | G107: 0.6 | H107: 2.2 | I107: z-ai/glm-4.5 | J107: OpenRouter catalogue
A108: Z.ai: GLM 4.5 Air | B108: Zhipu AI / Z.ai | C108: China | D108: Open | E108: MIT | F108: 131072 | G108: 0.13 | H108: 0.85 | I108: z-ai/glm-4.5-air | J108: OpenRouter catalogue
A109: Z.ai: GLM 4.5V | B109: Zhipu AI / Z.ai | C109: China | D109: Open | E109: MIT | F109: 65536 | G109: 0.6 | H109: 1.8 | I109: z-ai/glm-4.5v | J109: OpenRouter catalogue
A110: Z.ai: GLM 4.6 | B110: Zhipu AI / Z.ai | C110: China | D110: Open | E110: MIT | F110: 204800 | G110: 0.5 | H110: 2 | I110: z-ai/glm-4.6 | J110: OpenRouter catalogue
A111: Z.ai: GLM 4.6V | B111: Zhipu AI / Z.ai | C111: China | D111: Open | E111: MIT | F111: 131072 | G111: 0.3 | H111: 0.9 | I111: z-ai/glm-4.6v | J111: OpenRouter catalogue
... A118: Z.ai: GLM 5V Turbo | B118: Zhipu AI / Z.ai | C118: China | D118: Open | E118: MIT | F118: 202752 | G118: 1.2 | H118: 4 | I118: z-ai/glm-5v-turbo | J118: OpenRouter catalogue
